{"name": "txmongomodel", "versions": {"0.0.3": {"version": "0.0.3", "python_constraint": "*", "released_at": "2013-04-27T08:52:10+00:00", "yanked": false, "dependencies": ["twisted", "txmongo"]}, "0.0.2": {"version": "0.0.2", "python_constraint": "*", "released_at": "2013-04-27T08:46:04+00:00", "yanked": false, "dependencies": ["twisted", "txmongo"]}, "0.0.1": {"version": "0.0.1", "python_constraint": "*", "released_at": "2013-04-27T07:57:17+00:00", "yanked": false, "dependencies": ["twisted", "txmongo"]}}}