{"name": "geoalchemy", "versions": {"0.7.2": {"version": "0.7.2", "python_constraint": "*", "released_at": "2013-04-09T11:25:23+00:00", "yanked": false, "dependencies": ["SQLAlchemy (>=0.6.1)"]}, "0.7.1": {"version": "0.7.1", "python_constraint": "*", "released_at": "2012-03-31T15:54:16+00:00", "yanked": false, "dependencies": ["SQLAlchemy (>=0.6.1)"]}, "0.7": {"version": "0.7", "python_constraint": "*", "released_at": "2012-03-28T16:34:58+00:00", "yanked": false, "dependencies": ["SQLAlchemy (>=0.6.1)"]}, "0.6": {"version": "0.6", "python_constraint": "*", "released_at": "2011-06-15T14:32:14+00:00", "yanked": false, "dependencies": ["SQLAlchemy (>=0.6.1)"]}, "0.5": {"version": "0.5", "python_constraint": "*", "released_at": "2011-02-05T22:16:12+00:00", "yanked": false, "dependencies": ["SQLAlchemy (>=0.6.1)"]}, "0.4.1": {"version": "0.4.1", "python_constraint": "*", "released_at": "2010-06-23T06:31:01+00:00", "yanked": false, "dependencies": ["SQLAlchemy (>=0.6.1)"]}, "0.4": {"version": "0.4", "python_constraint": "*", "released_at": "2010-06-22T09:21:18+00:00", "yanked": false, "dependencies": ["SQLAlchemy (>=0.6.1)"]}, "0.3.1": {"version": "0.3.1", "python_constraint": "*", "released_at": "2010-06-05T21:13:56+00:00", "yanked": false, "dependencies": ["SQLAlchemy (>=0.6.1)"]}, "0.3": {"version": "0.3", "python_constraint": "*", "released_at": "2010-06-02T20:46:32+00:00", "yanked": false, "dependencies": ["SQLAlchemy (>=0.6.1)"]}, "0.2": {"version": "0.2", "python_constraint": "*", "released_at": "2010-05-05T19:33:37+00:00", "yanked": false, "dependencies": ["SQLAlchemy (>=0.6)"]}, "0.1.1": {"version": "0.1.1", "python_constraint": "*", "released_at": "2010-03-24T15:32:21+00:00", "yanked": false, "dependencies": ["SQLAlchemy (>=0.5)"]}, "0.1": {"version": "0.1", "python_constraint": "*", "released_at": "2009-10-04T11:57:59+00:00", "yanked": false, "dependencies": ["SQLAlchemy (>=0.5)"]}}}