{"name": "geti-sdk", "versions": {"1.5.6": {"version": "1.5.6", "python_constraint": ">=3.8", "released_at": "2023-05-23T14:37:59+00:00", "yanked": false, "dependencies": ["black (>=22.6) ; extra == \"dev\"", "certifi (>=2022.12.7)", "datumaro (==1.2.*)", "flake8 (>=4.0) ; extra == \"dev\"", "ipython (==8.12.*)", "ipywidgets (>=8.0.0) ; extra == \"notebooks\"", "isort (>=5.10) ; extra == \"dev\"", "joblib (>=1.1.1)", "jupyter-core (>=4.11.2) ; extra == \"notebooks\"", "jupyterlab (>=3.5.3) ; extra == \"notebooks\"", "mistune (>=2.0.3) ; extra == \"notebooks\"", "myst-parser (>=0.18) ; extra == \"docs\"", "nbqa (>=1.4.0) ; extra == \"dev\"", "numpy (==1.22.*)", "omegaconf (==2.3.*)", "opencv-python (==4.5.*)", "openmodelzoo-modelapi (==2022.3.*)", "openvino (==2022.3.0)", "orjson (==3.8.8)", "otx (==1.2.*)", "ovmsclient (>=2022.3)", "pathvalidate (>=2.5.0)", "Pillow (==9.5.*)", "pre-commit (>=2.20.0) ; extra == \"dev\"", "protobuf (>=3.20.2)", "pydocstyle (>=6.1) ; extra == \"dev\"", "pytest (==7.3.*) ; extra == \"dev\"", "pytest-cov (==4.0.*) ; extra == \"dev\"", "pytest-env (==0.8.*) ; extra == \"dev\"", "pytest-html (==3.2.*) ; extra == \"dev\"", "pytest-mock (>=3.10.0) ; extra == \"dev\"", "pytest-recording (==0.12.*) ; extra == \"dev\"", "python-dotenv (==1.0.*)", "requests (==2.31.*)", "simplejson (==3.19.*)", "sphinx (>=4.5) ; extra == \"docs\"", "sphinx-rtd-theme (>=1.0) ; extra == \"docs\"", "tqdm (==4.65.*)", "vcrpy (==4.2.*) ; extra == \"dev\""]}, "1.5.5": {"version": "1.5.5", "python_constraint": ">=3.8", "released_at": "2023-05-15T14:05:18+00:00", "yanked": false, "dependencies": ["black (>=22.6) ; extra == \"dev\"", "certifi (>=2022.12.7)", "datumaro (==1.2.*)", "flake8 (>=4.0) ; extra == \"dev\"", "ipython (==8.12.*)", "ipywidgets (>=8.0.0) ; extra == \"notebooks\"", "isort (>=5.10) ; extra == \"dev\"", "joblib (>=1.1.1)", "jupyter-core (>=4.11.2) ; extra == \"notebooks\"", "jupyterlab (>=3.5.3) ; extra == \"notebooks\"", "mistune (>=2.0.3) ; extra == \"notebooks\"", "myst-parser (>=0.18) ; extra == \"docs\"", "nbqa (>=1.4.0) ; extra == \"dev\"", "numpy (==1.22.*)", "omegaconf (==2.3.*)", "opencv-python (==4.5.*)", "openmodelzoo-modelapi (==2022.3.*)", "openvino (==2022.3.0)", "orjson (==3.8.8)", "otx (==1.2.*)", "ovmsclient (>=2022.3)", "pathvalidate (>=2.5.0)", "Pillow (==9.5.*)", "pre-commit (>=2.20.0) ; extra == \"dev\"", "protobuf (>=3.20.2)", "pydocstyle (>=6.1) ; extra == \"dev\"", "pytest (==7.3.*) ; extra == \"dev\"", "pytest-cov (==4.0.*) ; extra == \"dev\"", "pytest-env (==0.8.*) ; extra == \"dev\"", "pytest-html (==3.2.*) ; extra == \"dev\"", "pytest-mock (>=3.10.0) ; extra == \"dev\"", "pytest-recording (==0.12.*) ; extra == \"dev\"", "python-dotenv (==1.0.*)", "requests (==2.28.*)", "simplejson (==3.19.*)", "sphinx (>=4.5) ; extra == \"docs\"", "sphinx-rtd-theme (>=1.0) ; extra == \"docs\"", "tqdm (==4.65.*)", "vcrpy (==4.2.*) ; extra == \"dev\""]}, "1.5.4": {"version": "1.5.4", "python_constraint": ">=3.8", "released_at": "2023-05-11T12:22:34+00:00", "yanked": false, "dependencies": ["black (>=22.6) ; extra == \"dev\"", "certifi (>=2022.12.7)", "datumaro (==1.2.*)", "flake8 (>=4.0) ; extra == \"dev\"", "ipython (==8.12.*)", "ipywidgets (>=8.0.0) ; extra == \"notebooks\"", "isort (>=5.10) ; extra == \"dev\"", "joblib (>=1.1.1)", "jupyter-core (>=4.11.2) ; extra == \"notebooks\"", "jupyterlab (>=3.5.3) ; extra == \"notebooks\"", "mistune (>=2.0.3) ; extra == \"notebooks\"", "myst-parser (>=0.18) ; extra == \"docs\"", "nbqa (>=1.4.0) ; extra == \"dev\"", "numpy (==1.22.*)", "omegaconf (==2.3.*)", "opencv-python (==4.5.*)", "openmodelzoo-modelapi (==2022.3.*)", "openvino (==2022.3.0)", "orjson (==3.8.8)", "otx (==1.2.*)", "ovmsclient (>=2022.3)", "pathvalidate (>=2.5.0)", "Pillow (==9.5.*)", "pre-commit (>=2.20.0) ; extra == \"dev\"", "protobuf (>=3.20.2)", "pydocstyle (>=6.1) ; extra == \"dev\"", "pytest (==7.3.*) ; extra == \"dev\"", "pytest-cov (==4.0.*) ; extra == \"dev\"", "pytest-env (==0.8.*) ; extra == \"dev\"", "pytest-html (==3.2.*) ; extra == \"dev\"", "pytest-mock (>=3.10.0) ; extra == \"dev\"", "pytest-recording (==0.12.*) ; extra == \"dev\"", "python-dotenv (==1.0.*)", "requests (==2.28.*)", "simplejson (==3.19.*)", "sphinx (>=4.5) ; extra == \"docs\"", "sphinx-rtd-theme (>=1.0) ; extra == \"docs\"", "tqdm (==4.65.*)", "vcrpy (==4.2.*) ; extra == \"dev\""]}, "1.5.3": {"version": "1.5.3", "python_constraint": ">=3.8", "released_at": "2023-05-10T12:10:25+00:00", "yanked": false, "dependencies": ["black (>=22.6) ; extra == \"dev\"", "certifi (>=2022.12.7)", "datumaro (==1.2.*)", "flake8 (>=4.0) ; extra == \"dev\"", "ipython (==8.12.*)", "ipywidgets (>=8.0.0) ; extra == \"notebooks\"", "isort (>=5.10) ; extra == \"dev\"", "joblib (>=1.1.1)", "jupyter-core (>=4.11.2) ; extra == \"notebooks\"", "jupyterlab (>=3.5.3) ; extra == \"notebooks\"", "mistune (>=2.0.3) ; extra == \"notebooks\"", "myst-parser (>=0.18) ; extra == \"docs\"", "nbqa (>=1.4.0) ; extra == \"dev\"", "numpy (==1.22.*)", "omegaconf (==2.3.*)", "opencv-python (==4.5.*)", "openmodelzoo-modelapi (==2022.3.*)", "openvino (==2022.3.0)", "orjson (==3.8.8)", "otx (==1.2.*)", "ovmsclient (>=2022.3)", "pathvalidate (>=2.5.0)", "Pillow (==9.5.*)", "pre-commit (>=2.20.0) ; extra == \"dev\"", "protobuf (>=3.20.2)", "pydocstyle (>=6.1) ; extra == \"dev\"", "pytest (==7.3.*) ; extra == \"dev\"", "pytest-cov (==4.0.*) ; extra == \"dev\"", "pytest-env (==0.8.*) ; extra == \"dev\"", "pytest-html (==3.2.*) ; extra == \"dev\"", "pytest-mock (>=3.10.0) ; extra == \"dev\"", "pytest-recording (==0.12.*) ; extra == \"dev\"", "python-dotenv (==1.0.*)", "requests (==2.28.*)", "simplejson (==3.19.*)", "sphinx (>=4.5) ; extra == \"docs\"", "sphinx-rtd-theme (>=1.0) ; extra == \"docs\"", "tqdm (==4.65.*)", "vcrpy (==4.2.*) ; extra == \"dev\""]}, "1.5.2": {"version": "1.5.2", "python_constraint": ">=3.8", "released_at": "2023-05-08T12:17:23+00:00", "yanked": false, "dependencies": ["black (>=22.6) ; extra == \"dev\"", "certifi (>=2022.12.7)", "datumaro (==1.2.*)", "flake8 (>=4.0) ; extra == \"dev\"", "ipython (==8.12.*)", "ipywidgets (>=8.0.0) ; extra == \"notebooks\"", "isort (>=5.10) ; extra == \"dev\"", "joblib (>=1.1.1)", "jupyter-core (>=4.11.2) ; extra == \"notebooks\"", "jupyterlab (>=3.5.3) ; extra == \"notebooks\"", "mistune (>=2.0.3) ; extra == \"notebooks\"", "myst-parser (>=0.18) ; extra == \"docs\"", "nbqa (>=1.4.0) ; extra == \"dev\"", "numpy (==1.22.*)", "omegaconf (==2.3.*)", "opencv-python (==4.5.*)", "openmodelzoo-modelapi (==2022.3.*)", "openvino (==2022.3.0)", "orjson (==3.8.8)", "otx (==1.2.*)", "ovmsclient (>=2022.3)", "pathvalidate (>=2.5.0)", "Pillow (==9.5.*)", "pre-commit (>=2.20.0) ; extra == \"dev\"", "protobuf (>=3.20.2)", "pydocstyle (>=6.1) ; extra == \"dev\"", "pytest (==7.2.*) ; extra == \"dev\"", "pytest-cov (==4.0.*) ; extra == \"dev\"", "pytest-env (==0.8.*) ; extra == \"dev\"", "pytest-html (==3.2.*) ; extra == \"dev\"", "pytest-mock (>=3.10.0) ; extra == \"dev\"", "pytest-recording (==0.12.*) ; extra == \"dev\"", "python-dotenv (==1.0.*)", "requests (==2.28.*)", "simplejson (==3.19.*)", "sphinx (>=4.5) ; extra == \"docs\"", "sphinx-rtd-theme (>=1.0) ; extra == \"docs\"", "tqdm (==4.65.*)", "vcrpy (==4.2.*) ; extra == \"dev\""]}, "1.5.1": {"version": "1.5.1", "python_constraint": ">=3.8", "released_at": "2023-04-26T14:33:22+00:00", "yanked": false, "dependencies": ["black (>=22.6) ; extra == \"dev\"", "certifi (>=2022.12.7)", "datumaro (==1.1.*)", "flake8 (>=4.0) ; extra == \"dev\"", "ipython (==8.12.*)", "ipywidgets (>=8.0.0) ; extra == \"notebooks\"", "isort (>=5.10) ; extra == \"dev\"", "joblib (>=1.1.1)", "jupyter-core (>=4.11.2) ; extra == \"notebooks\"", "jupyterlab (>=3.5.3) ; extra == \"notebooks\"", "mistune (>=2.0.3) ; extra == \"notebooks\"", "myst-parser (>=0.18) ; extra == \"docs\"", "nbqa (>=1.4.0) ; extra == \"dev\"", "numpy (==1.22.*)", "omegaconf (==2.3.*)", "opencv-python (==4.5.*)", "openmodelzoo-modelapi (==2022.3.*)", "openvino (==2022.3.0)", "orjson (==3.8.8)", "otx (==1.2.0)", "ovmsclient (>=2022.3)", "pathvalidate (>=2.5.0)", "Pillow (==9.5.*)", "pre-commit (>=2.20.0) ; extra == \"dev\"", "protobuf (>=3.20.2)", "pydocstyle (>=6.1) ; extra == \"dev\"", "pytest (==7.2.*) ; extra == \"dev\"", "pytest-cov (==4.0.*) ; extra == \"dev\"", "pytest-env (==0.8.*) ; extra == \"dev\"", "pytest-html (==3.2.*) ; extra == \"dev\"", "pytest-mock (>=3.10.0) ; extra == \"dev\"", "pytest-recording (==0.12.*) ; extra == \"dev\"", "python-dotenv (==1.0.*)", "requests (==2.28.*)", "simplejson (==3.19.*)", "sphinx (>=4.5) ; extra == \"docs\"", "sphinx-rtd-theme (>=1.0) ; extra == \"docs\"", "tqdm (==4.65.*)", "vcrpy (==4.2.*) ; extra == \"dev\""]}, "1.5.0": {"version": "1.5.0", "python_constraint": ">=3.8", "released_at": "2023-04-24T09:21:49+00:00", "yanked": false, "dependencies": ["black (>=22.6) ; extra == \"dev\"", "certifi (>=2022.12.7)", "datumaro (==1.1.*)", "flake8 (>=4.0) ; extra == \"dev\"", "ipython (==8.11.*)", "ipywidgets (>=8.0.0) ; extra == \"notebooks\"", "isort (>=5.10) ; extra == \"dev\"", "joblib (>=1.1.1)", "jupyter-core (>=4.11.2) ; extra == \"notebooks\"", "jupyterlab (>=3.5.3) ; extra == \"notebooks\"", "mistune (>=2.0.3) ; extra == \"notebooks\"", "myst-parser (>=0.18) ; extra == \"docs\"", "nbqa (>=1.4.0) ; extra == \"dev\"", "numpy (==1.22.*)", "omegaconf (==2.3.*)", "opencv-python (==4.5.*)", "openmodelzoo-modelapi (==2022.3.*)", "openvino (==2022.3.0)", "orjson (==3.8.8)", "otx (==1.1.2)", "ovmsclient (>=2022.3)", "pathvalidate (>=2.5.0)", "Pillow (==9.5.*)", "pre-commit (>=2.20.0) ; extra == \"dev\"", "protobuf (>=3.20.2)", "pydocstyle (>=6.1) ; extra == \"dev\"", "pytest (==7.2.*) ; extra == \"dev\"", "pytest-cov (==4.0.*) ; extra == \"dev\"", "pytest-env (==0.8.*) ; extra == \"dev\"", "pytest-html (==3.2.*) ; extra == \"dev\"", "pytest-mock (>=3.10.0) ; extra == \"dev\"", "pytest-recording (==0.12.*) ; extra == \"dev\"", "python-dotenv (==1.0.*)", "requests (==2.28.*)", "simplejson (==3.19.*)", "sphinx (>=4.5) ; extra == \"docs\"", "sphinx-rtd-theme (>=1.0) ; extra == \"docs\"", "tqdm (==4.65.*)", "vcrpy (==4.2.*) ; extra == \"dev\""]}, "1.4.1": {"version": "1.4.1", "python_constraint": ">=3.8", "released_at": "2023-04-12T09:01:40+00:00", "yanked": false, "dependencies": ["black (>=22.6) ; extra == \"dev\"", "certifi (>=2022.12.7)", "datumaro (==1.0.*)", "flake8 (>=4.0) ; extra == \"dev\"", "ipython (==8.11.*)", "ipywidgets (>=8.0.0) ; extra == \"notebooks\"", "isort (>=5.10) ; extra == \"dev\"", "joblib (>=1.1.1)", "jupyter-core (>=4.11.2) ; extra == \"notebooks\"", "jupyterlab (>=3.5.3) ; extra == \"notebooks\"", "mistune (>=2.0.3) ; extra == \"notebooks\"", "myst-parser (>=0.18) ; extra == \"docs\"", "nbqa (>=1.4.0) ; extra == \"dev\"", "numpy (==1.22.*)", "omegaconf (==2.1.*)", "opencv-python (==4.5.*)", "openmodelzoo-modelapi (==2022.3.*)", "openvino (==2022.3.0)", "orjson (==3.8.8)", "otx (==1.1.0)", "ovmsclient (>=2022.3)", "pathvalidate (>=2.5.0)", "Pillow (==9.4.*)", "pre-commit (>=2.20.0) ; extra == \"dev\"", "protobuf (>=3.20.2)", "pydocstyle (>=6.1) ; extra == \"dev\"", "pytest (==7.2.*) ; extra == \"dev\"", "pytest-cov (==4.0.*) ; extra == \"dev\"", "pytest-env (==0.8.*) ; extra == \"dev\"", "pytest-html (==3.2.*) ; extra == \"dev\"", "pytest-mock (>=3.10.0) ; extra == \"dev\"", "pytest-recording (==0.12.*) ; extra == \"dev\"", "python-dotenv (==1.0.*)", "requests (==2.28.*)", "simplejson (==3.18.*)", "sphinx (>=4.5) ; extra == \"docs\"", "sphinx-rtd-theme (>=1.0) ; extra == \"docs\"", "tqdm (==4.65.*)", "vcrpy (==4.2.*) ; extra == \"dev\""]}}}