{"name": "inaction", "versions": {"1.0.3": {"version": "1.0.3", "python_constraint": "*", "released_at": "2013-06-14T09:51:49+00:00", "yanked": false, "dependencies": ["pyinotify"]}, "1.0.2": {"version": "1.0.2", "python_constraint": "*", "released_at": "2013-06-14T09:04:44+00:00", "yanked": false, "dependencies": ["pyinotify"]}, "1.0.1": {"version": "1.0.1", "python_constraint": "*", "released_at": "2013-06-12T15:01:09+00:00", "yanked": false, "dependencies": ["pyinotify"]}, "1.0": {"version": "1.0", "python_constraint": "*", "released_at": "2013-06-12T08:52:32+00:00", "yanked": false, "dependencies": ["pyinotify"]}}}