{"name": "virtualenvwrapper-powershell", "versions": {"12.7.8": {"version": "12.7.8", "python_constraint": "*", "released_at": "2012-07-08T14:42:41+00:00", "yanked": false, "dependencies": []}, "12.1.1": {"version": "12.1.1", "python_constraint": "*", "released_at": "2012-01-01T23:29:42+00:00", "yanked": false, "dependencies": []}, "11.9.25": {"version": "11.9.25", "python_constraint": "*", "released_at": "2011-09-25T20:29:46+00:00", "yanked": false, "dependencies": []}, "11.8.28": {"version": "11.8.28", "python_constraint": "*", "released_at": "2011-08-28T16:20:45+00:00", "yanked": false, "dependencies": []}, "2.7.3": {"version": "2.7.3", "python_constraint": "*", "released_at": "2011-06-28T19:43:24+00:00", "yanked": false, "dependencies": ["virtualenv"]}, "2.7.2": {"version": "2.7.2", "python_constraint": "*", "released_at": "2011-06-27T23:24:17+00:00", "yanked": false, "dependencies": ["virtualenv"]}, "2.7.1": {"version": "2.7.1", "python_constraint": "*", "released_at": "2011-05-29T13:12:29+00:00", "yanked": false, "dependencies": ["virtualenv"]}}}