{"name": "wisdomweaver", "versions": {"0.3.0": {"version": "0.3.0", "python_constraint": ">=3.9", "released_at": "2023-05-23T21:49:39+00:00", "yanked": false, "dependencies": ["black ; extra == \"dev\"", "bumpver ; extra == \"dev\"", "html2text", "isort ; extra == \"dev\"", "pip-tools ; extra == \"dev\"", "pytest ; extra == \"dev\""]}, "0.1.0": {"version": "0.1.0", "python_constraint": ">=3.9", "released_at": "2023-05-23T16:36:51+00:00", "yanked": false, "dependencies": ["black ; extra == \"dev\"", "bumpver ; extra == \"dev\"", "html2text", "isort ; extra == \"dev\"", "pip-tools ; extra == \"dev\"", "pytest ; extra == \"dev\""]}}}