{"name": "dctrackclient", "versions": {"0.6.0": {"version": "0.6.0", "python_constraint": ">=3.7", "released_at": "2023-05-23T19:23:57+00:00", "yanked": false, "dependencies": []}, "0.5.2": {"version": "0.5.2", "python_constraint": ">=3.7", "released_at": "2023-05-19T17:52:06+00:00", "yanked": false, "dependencies": []}, "0.5.1": {"version": "0.5.1", "python_constraint": ">=3.7", "released_at": "2023-05-19T17:27:24+00:00", "yanked": false, "dependencies": []}, "0.5.0": {"version": "0.5.0", "python_constraint": ">=3.7", "released_at": "2023-05-18T20:31:06+00:00", "yanked": false, "dependencies": []}, "0.4.4": {"version": "0.4.4", "python_constraint": ">=3.7", "released_at": "2023-05-17T23:23:40+00:00", "yanked": false, "dependencies": []}, "0.4.3": {"version": "0.4.3", "python_constraint": ">=3.7", "released_at": "2023-05-17T22:57:52+00:00", "yanked": false, "dependencies": []}, "0.4.2": {"version": "0.4.2", "python_constraint": ">=3.7", "released_at": "2023-05-17T22:42:19+00:00", "yanked": false, "dependencies": []}, "0.4.1": {"version": "0.4.1", "python_constraint": ">=3.7", "released_at": "2023-05-17T22:35:09+00:00", "yanked": false, "dependencies": []}, "0.4.0": {"version": "0.4.0", "python_constraint": ">=3.7", "released_at": "2023-05-17T22:24:31+00:00", "yanked": false, "dependencies": []}, "0.3.4": {"version": "0.3.4", "python_constraint": ">=3.7", "released_at": "2023-05-17T18:56:29+00:00", "yanked": false, "dependencies": []}, "0.3.3": {"version": "0.3.3", "python_constraint": ">=3.7", "released_at": "2023-05-17T18:30:12+00:00", "yanked": false, "dependencies": []}, "0.3.2": {"version": "0.3.2", "python_constraint": ">=3.7", "released_at": "2023-05-17T17:28:28+00:00", "yanked": false, "dependencies": []}, "0.3.1": {"version": "0.3.1", "python_constraint": ">=3.7", "released_at": "2023-05-17T16:42:06+00:00", "yanked": false, "dependencies": []}, "0.3.0": {"version": "0.3.0", "python_constraint": ">=3.7", "released_at": "2023-05-17T00:07:30+00:00", "yanked": false, "dependencies": []}, "0.2.4": {"version": "0.2.4", "python_constraint": ">=3.7", "released_at": "2023-04-24T21:17:44+00:00", "yanked": false, "dependencies": []}, "0.2.3": {"version": "0.2.3", "python_constraint": ">=3.7", "released_at": "2023-04-21T15:51:04+00:00", "yanked": false, "dependencies": []}, "0.2.2": {"version": "0.2.2", "python_constraint": ">=3.7", "released_at": "2023-04-20T21:53:02+00:00", "yanked": false, "dependencies": []}, "0.2.1": {"version": "0.2.1", "python_constraint": ">=3.7", "released_at": "2023-04-20T14:32:36+00:00", "yanked": false, "dependencies": []}, "0.2.0": {"version": "0.2.0", "python_constraint": ">=3.7", "released_at": "2023-04-19T22:13:21+00:00", "yanked": false, "dependencies": []}, "0.1.2": {"version": "0.1.2", "python_constraint": ">=3.7", "released_at": "2023-04-12T18:15:54+00:00", "yanked": false, "dependencies": []}, "0.1.1": {"version": "0.1.1", "python_constraint": ">=3.7", "released_at": "2023-04-11T00:47:50+00:00", "yanked": false, "dependencies": []}, "0.1.0": {"version": "0.1.0", "python_constraint": ">=3.7", "released_at": "2023-04-11T00:37:31+00:00", "yanked": false, "dependencies": []}, "0.0.3": {"version": "0.0.3", "python_constraint": ">=3.7", "released_at": "2023-04-10T23:52:14+00:00", "yanked": false, "dependencies": []}, "0.0.2": {"version": "0.0.2", "python_constraint": ">=3.7", "released_at": "2023-04-10T23:50:47+00:00", "yanked": false, "dependencies": []}, "0.0.1": {"version": "0.0.1", "python_constraint": ">=3.7", "released_at": "2023-04-10T23:34:24+00:00", "yanked": false, "dependencies": []}, "0.0.0": {"version": "0.0.0", "python_constraint": ">=3.7", "released_at": "2023-04-10T23:25:13+00:00", "yanked": false, "dependencies": []}}}