{"name": "mdx-semanticwikilinks", "versions": {"1.1.1": {"version": "1.1.1", "python_constraint": "*", "released_at": "2012-08-15T14:20:19+00:00", "yanked": false, "dependencies": ["Markdown (>=2.0)"]}, "1.1": {"version": "1.1", "python_constraint": "*", "released_at": "2012-08-15T14:10:21+00:00", "yanked": false, "dependencies": ["Markdown (>=2.0)"]}, "1.0": {"version": "1.0", "python_constraint": "*", "released_at": "2012-04-27T16:41:11+00:00", "yanked": false, "dependencies": ["Markdown (>=2.0)"]}}}