{"name": "collective-wpadmin", "versions": {"1.0a3": {"version": "1.0a3", "python_constraint": "*", "released_at": "2013-01-17T12:41:59+00:00", "yanked": false, "dependencies": ["collective.configviews", "collective.js.datatables", "collective.js.jqueryui", "collective.quickupload", "plone.api", "plone.app.testing ; extra == \"tests\"", "plone.formwidget.namedfile", "plone.namedfile", "setuptools"]}, "1.0a2": {"version": "1.0a2", "python_constraint": "*", "released_at": "2013-01-17T07:56:02+00:00", "yanked": false, "dependencies": ["collective.configviews", "collective.js.datatables", "collective.js.jqueryui", "collective.quickupload", "plone.api", "plone.app.testing ; extra == \"tests\"", "plone.formwidget.namedfile", "plone.namedfile", "setuptools"]}, "1.0a1": {"version": "1.0a1", "python_constraint": "*", "released_at": "2013-01-16T14:46:54+00:00", "yanked": false, "dependencies": ["collective.configviews", "collective.googleanalytics", "collective.js.datatables", "collective.js.jqueryui", "collective.quickupload", "plone.api", "plone.app.testing ; extra == \"tests\"", "plone.formwidget.namedfile", "plone.namedfile", "setuptools"]}}}