{"name": "collective-ptg-nivoslider", "versions": {"1.0.6": {"version": "1.0.6", "python_constraint": "*", "released_at": "2012-07-26T15:08:35+00:00", "yanked": false, "dependencies": ["collective.plonetruegallery", "setuptools"]}, "1.0.5": {"version": "1.0.5", "python_constraint": "*", "released_at": "2012-07-26T15:03:14+00:00", "yanked": false, "dependencies": ["collective.plonetruegallery", "setuptools"]}, "1.0.3": {"version": "1.0.3", "python_constraint": "*", "released_at": "2012-07-24T15:05:32+00:00", "yanked": false, "dependencies": ["collective.plonetruegallery", "setuptools"]}, "1.0.1": {"version": "1.0.1", "python_constraint": "*", "released_at": "2012-07-04T13:05:38+00:00", "yanked": false, "dependencies": ["collective.plonetruegallery", "setuptools"]}, "1.0": {"version": "1.0", "python_constraint": "*", "released_at": "2012-07-03T21:50:43+00:00", "yanked": false, "dependencies": ["collective.plonetruegallery", "setuptools"]}}}