{"name": "concatenate-files", "versions": {"1.2": {"version": "1.2", "python_constraint": "*", "released_at": "2012-06-16T23:50:10+00:00", "yanked": false, "dependencies": []}, "1.1.1": {"version": "1.1.1", "python_constraint": "*", "released_at": "2012-05-07T04:25:19+00:00", "yanked": false, "dependencies": []}, "1.1": {"version": "1.1", "python_constraint": "*", "released_at": "2012-04-28T23:04:04+00:00", "yanked": false, "dependencies": []}, "1.0.2": {"version": "1.0.2", "python_constraint": "*", "released_at": "2012-02-19T23:59:23+00:00", "yanked": false, "dependencies": []}, "1.0.1": {"version": "1.0.1", "python_constraint": "*", "released_at": "2012-02-18T20:31:50+00:00", "yanked": false, "dependencies": []}, "1.0": {"version": "1.0", "python_constraint": "*", "released_at": "2012-02-18T20:26:15+00:00", "yanked": false, "dependencies": []}}}