{"name": "django-lastfm-auth", "versions": {"0.2.3": {"version": "0.2.3", "python_constraint": "*", "released_at": "2011-10-08T20:16:50+00:00", "yanked": false, "dependencies": ["django-social-auth (>=0.3.3)"]}, "0.2.2": {"version": "0.2.2", "python_constraint": "*", "released_at": "2011-10-08T18:23:01+00:00", "yanked": false, "dependencies": ["django-social-auth (>=0.3.3)"]}, "0.2.1": {"version": "0.2.1", "python_constraint": "*", "released_at": "2011-10-02T14:58:15+00:00", "yanked": false, "dependencies": ["django-social-auth (>=0.3.3)"]}, "0.2": {"version": "0.2", "python_constraint": "*", "released_at": "2011-09-27T03:05:51+00:00", "yanked": false, "dependencies": ["django-social-auth (>=0.3.3)"]}, "0.1.1": {"version": "0.1.1", "python_constraint": "*", "released_at": "2011-09-10T01:51:07+00:00", "yanked": false, "dependencies": ["django-social-auth (>=0.3.3)"]}, "0.1": {"version": "0.1", "python_constraint": "*", "released_at": "2011-09-09T21:31:43+00:00", "yanked": false, "dependencies": ["django-social-auth (>=0.3.3)"]}}}