{"name": "django-cccontact", "versions": {"1.6.4": {"version": "1.6.4", "python_constraint": "*", "released_at": "2012-10-08T15:51:40+00:00", "yanked": false, "dependencies": ["django-mailer (==0.2a1)"]}, "1.6.3": {"version": "1.6.3", "python_constraint": "*", "released_at": "2012-09-24T09:19:13+00:00", "yanked": false, "dependencies": []}, "1.6.2": {"version": "1.6.2", "python_constraint": "*", "released_at": "2012-09-24T08:23:46+00:00", "yanked": false, "dependencies": []}, "1.6.0": {"version": "1.6.0", "python_constraint": "*", "released_at": "2012-09-03T05:40:48+00:00", "yanked": false, "dependencies": []}, "0.0.4": {"version": "0.0.4", "python_constraint": "*", "released_at": "2012-06-27T11:39:48+00:00", "yanked": false, "dependencies": []}, "0.0.3": {"version": "0.0.3", "python_constraint": "*", "released_at": "2012-06-13T19:01:59+00:00", "yanked": false, "dependencies": []}, "0.0.2": {"version": "0.0.2", "python_constraint": "*", "released_at": "2012-06-13T18:20:49+00:00", "yanked": false, "dependencies": []}}}