{"name": "django-staticmedia", "versions": {"0.2.2": {"version": "0.2.2", "python_constraint": "*", "released_at": "2010-07-03T18:53:32+00:00", "yanked": false, "dependencies": []}, "0.2.1": {"version": "0.2.1", "python_constraint": "*", "released_at": "2009-10-22T17:49:43+00:00", "yanked": false, "dependencies": []}, "0.2": {"version": "0.2", "python_constraint": "*", "released_at": "2009-03-18T22:03:14+00:00", "yanked": false, "dependencies": []}, "0.1.4": {"version": "0.1.4", "python_constraint": "*", "released_at": "2009-02-06T23:25:57+00:00", "yanked": false, "dependencies": []}, "0.1.3": {"version": "0.1.3", "python_constraint": "*", "released_at": "2009-02-04T16:43:44+00:00", "yanked": false, "dependencies": []}, "0.1.2": {"version": "0.1.2", "python_constraint": "*", "released_at": "2009-02-04T03:41:49+00:00", "yanked": false, "dependencies": []}, "0.1.1": {"version": "0.1.1", "python_constraint": "*", "released_at": "2009-01-30T16:35:03+00:00", "yanked": false, "dependencies": []}, "0.1": {"version": "0.1", "python_constraint": "*", "released_at": "2009-01-30T00:29:28+00:00", "yanked": false, "dependencies": []}}}