{"name": "django-coverage", "versions": {"1.2.4": {"version": "1.2.4", "python_constraint": "*", "released_at": "2013-06-01T12:26:28+00:00", "yanked": false, "dependencies": []}, "1.2.2": {"version": "1.2.2", "python_constraint": "*", "released_at": "2012-01-03T18:13:16+00:00", "yanked": false, "dependencies": []}, "1.2.1": {"version": "1.2.1", "python_constraint": "*", "released_at": "2011-08-12T21:59:44+00:00", "yanked": false, "dependencies": []}, "1.2": {"version": "1.2", "python_constraint": "*", "released_at": "2011-03-24T10:47:13+00:00", "yanked": false, "dependencies": []}, "1.1.1": {"version": "1.1.1", "python_constraint": "*", "released_at": "2011-01-21T08:55:30+00:00", "yanked": false, "dependencies": []}, "1.1": {"version": "1.1", "python_constraint": "*", "released_at": "2010-11-02T20:28:11+00:00", "yanked": false, "dependencies": []}, "1.0.3": {"version": "1.0.3", "python_constraint": "*", "released_at": "2010-11-02T20:29:06+00:00", "yanked": false, "dependencies": []}, "1.0.2": {"version": "1.0.2", "python_constraint": "*", "released_at": "2010-10-18T14:10:46+00:00", "yanked": false, "dependencies": []}, "1.0.1": {"version": "1.0.1", "python_constraint": "*", "released_at": "2009-11-29T16:19:32+00:00", "yanked": false, "dependencies": []}, "1.0": {"version": "1.0", "python_constraint": "*", "released_at": "2009-11-29T15:55:00+00:00", "yanked": false, "dependencies": []}}}