{"name": "btools", "versions": {"0.999999": {"version": "0.999999", "python_constraint": "*", "released_at": "2009-09-17T06:36:45+00:00", "yanked": false, "dependencies": []}, "0.99999": {"version": "0.99999", "python_constraint": "*", "released_at": "2009-09-07T06:41:30+00:00", "yanked": false, "dependencies": []}, "0.9999": {"version": "0.9999", "python_constraint": "*", "released_at": "2009-09-02T05:30:35+00:00", "yanked": false, "dependencies": []}, "0.999": {"version": "0.999", "python_constraint": "*", "released_at": "2009-08-26T04:48:40+00:00", "yanked": false, "dependencies": []}}}