{"name": "cheetah", "versions": {"2.4.4": {"version": "2.4.4", "python_constraint": "*", "released_at": "2010-12-13T04:50:20+00:00", "yanked": false, "dependencies": ["Markdown (>=2.0.1)"]}, "2.4.3": {"version": "2.4.3", "python_constraint": "*", "released_at": "2010-09-16T20:21:50+00:00", "yanked": false, "dependencies": ["Markdown (>=2.0.1)"]}, "2.4.2.1": {"version": "2.4.2.1", "python_constraint": "*", "released_at": "2010-03-01T06:12:47+00:00", "yanked": false, "dependencies": ["Markdown (>=2.0.1)"]}, "2.4.2": {"version": "2.4.2", "python_constraint": "*", "released_at": "2010-02-08T05:20:15+00:00", "yanked": false, "dependencies": ["Markdown (>=2.0.1)"]}, "2.4.1": {"version": "2.4.1", "python_constraint": "*", "released_at": "2009-12-20T00:31:45+00:00", "yanked": false, "dependencies": ["Markdown (>=2.0.1)"]}, "2.4.0": {"version": "2.4.0", "python_constraint": "*", "released_at": "2009-10-25T02:46:16+00:00", "yanked": false, "dependencies": ["Markdown (>=2.0.1)"]}, "2.3.0": {"version": "2.3.0", "python_constraint": "*", "released_at": "2009-10-25T02:52:14+00:00", "yanked": false, "dependencies": ["Markdown (>=2.0.1)"]}, "2.2.2": {"version": "2.2.2", "python_constraint": "*", "released_at": "2009-09-15T01:12:18+00:00", "yanked": false, "dependencies": ["Markdown (>=2.0.1)"]}, "2.2.1": {"version": "2.2.1", "python_constraint": "*", "released_at": "2009-07-02T20:02:37+00:00", "yanked": false, "dependencies": []}, "1.0": {"version": "1.0", "python_constraint": "*", "released_at": "2006-01-26T17:39:58+00:00", "yanked": false, "dependencies": []}}}