{"name": "tf-nightly-macos", "versions": {"2.14.0.dev20230523": {"version": "2.14.0.dev20230523", "python_constraint": ">=3.8", "released_at": "2023-05-23T16:40:36+00:00", "yanked": false, "dependencies": ["absl-py (>=1.0.0)", "astunparse (>=1.6.0)", "flatbuffers (>=23.1.21)", "gast (>=0.2.1,<=0.4.0)", "google-pasta (>=0.1.1)", "grpcio (>=1.24.3,<2.0)", "h5py (>=2.9.0)", "keras (>=2.13.1rc0,<2.14)", "libclang (>=13.0.0)", "numpy (>=1.22)", "opt-einsum (>=2.3.2)", "packaging", "protobuf (>=3.20.3,!=4.21.0,!=4.21.1,!=4.21.2,!=4.21.3,!=4.21.4,!=4.21.5,<5.0.0dev)", "setuptools", "six (>=1.12.0)", "tensorboard (>=2.13,<2.14)", "tensorflow-estimator (>=2.13.0rc0,<2.14)", "tensorflow-io-gcs-filesystem (>=0.23.1) ; platform_machine != \"arm64\" or platform_system != \"Darwin\"", "termcolor (>=1.1.0)", "typing-extensions (>=3.6.6)", "wrapt (>=1.11.0)"]}, "2.14.0.dev20230518": {"version": "2.14.0.dev20230518", "python_constraint": ">=3.8", "released_at": "2023-05-19T04:39:11+00:00", "yanked": false, "dependencies": ["absl-py (>=1.0.0)", "astunparse (>=1.6.0)", "flatbuffers (>=23.1.21)", "gast (>=0.2.1,<=0.4.0)", "google-pasta (>=0.1.1)", "grpcio (>=1.24.3,<2.0)", "h5py (>=2.9.0)", "keras (>=2.13.1rc0,<2.14)", "libclang (>=13.0.0)", "numpy (>=1.22)", "opt-einsum (>=2.3.2)", "packaging", "protobuf (>=3.20.3,!=4.21.0,!=4.21.1,!=4.21.2,!=4.21.3,!=4.21.4,!=4.21.5,<5.0.0dev)", "setuptools", "six (>=1.12.0)", "tensorboard (>=2.13,<2.14)", "tensorflow-estimator (>=2.13.0rc0,<2.14)", "tensorflow-io-gcs-filesystem (>=0.23.1) ; platform_machine != \"arm64\" or platform_system != \"Darwin\"", "termcolor (>=1.1.0)", "typing-extensions (>=3.6.6)", "wrapt (>=1.11.0)"]}, "2.14.0.dev20230517": {"version": "2.14.0.dev20230517", "python_constraint": ">=3.8", "released_at": "2023-05-18T04:38:12+00:00", "yanked": false, "dependencies": ["absl-py (>=1.0.0)", "astunparse (>=1.6.0)", "flatbuffers (>=23.1.21)", "gast (>=0.2.1,<=0.4.0)", "google-pasta (>=0.1.1)", "grpcio (>=1.24.3,<2.0)", "h5py (>=2.9.0)", "keras (>=2.13.1rc0,<2.14)", "libclang (>=13.0.0)", "numpy (>=1.22)", "opt-einsum (>=2.3.2)", "packaging", "protobuf (>=3.20.3,!=4.21.0,!=4.21.1,!=4.21.2,!=4.21.3,!=4.21.4,!=4.21.5,<5.0.0dev)", "setuptools", "six (>=1.12.0)", "tensorboard (>=2.13,<2.14)", "tensorflow-estimator (>=2.13.0rc0,<2.14)", "tensorflow-io-gcs-filesystem (>=0.23.1) ; platform_machine != \"arm64\" or platform_system != \"Darwin\"", "termcolor (>=1.1.0)", "typing-extensions (>=3.6.6)", "wrapt (>=1.11.0,<1.15)"]}, "2.14.0.dev20230516": {"version": "2.14.0.dev20230516", "python_constraint": ">=3.8", "released_at": "2023-05-17T04:38:15+00:00", "yanked": false, "dependencies": ["absl-py (>=1.0.0)", "astunparse (>=1.6.0)", "flatbuffers (>=23.1.21)", "gast (>=0.2.1,<=0.4.0)", "google-pasta (>=0.1.1)", "grpcio (>=1.24.3,<2.0)", "h5py (>=2.9.0)", "keras (>=2.13.1rc0,<2.14)", "libclang (>=13.0.0)", "numpy (>=1.22)", "opt-einsum (>=2.3.2)", "packaging", "protobuf (>=3.20.3,!=4.21.0,!=4.21.1,!=4.21.2,!=4.21.3,!=4.21.4,!=4.21.5,<5.0.0dev)", "setuptools", "six (>=1.12.0)", "tensorboard (>=2.13,<2.14)", "tensorflow-estimator (>=2.13.0rc0,<2.14)", "tensorflow-io-gcs-filesystem (>=0.23.1) ; platform_machine != \"arm64\" or platform_system != \"Darwin\"", "termcolor (>=1.1.0)", "typing-extensions (>=3.6.6)", "wrapt (>=1.11.0,<1.15)"]}, "2.14.0.dev20230515": {"version": "2.14.0.dev20230515", "python_constraint": ">=3.8", "released_at": "2023-05-16T04:38:16+00:00", "yanked": false, "dependencies": ["absl-py (>=1.0.0)", "astunparse (>=1.6.0)", "flatbuffers (>=23.1.21)", "gast (>=0.2.1,<=0.4.0)", "google-pasta (>=0.1.1)", "grpcio (>=1.24.3,<2.0)", "h5py (>=2.9.0)", "keras (>=2.13.1rc0,<2.14)", "libclang (>=13.0.0)", "numpy (>=1.22)", "opt-einsum (>=2.3.2)", "packaging", "protobuf (>=3.20.3,!=4.21.0,!=4.21.1,!=4.21.2,!=4.21.3,!=4.21.4,!=4.21.5,<5.0.0dev)", "setuptools", "six (>=1.12.0)", "tensorboard (>=2.13,<2.14)", "tensorflow-estimator (>=2.13.0rc0,<2.14)", "tensorflow-io-gcs-filesystem (>=0.23.1) ; platform_machine != \"arm64\" or platform_system != \"Darwin\"", "termcolor (>=1.1.0)", "typing-extensions (>=3.6.6)", "wrapt (>=1.11.0,<1.15)"]}, "2.14.0.dev20230514": {"version": "2.14.0.dev20230514", "python_constraint": ">=3.8", "released_at": "2023-05-15T04:36:54+00:00", "yanked": false, "dependencies": ["absl-py (>=1.0.0)", "astunparse (>=1.6.0)", "flatbuffers (>=23.1.21)", "gast (>=0.2.1,<=0.4.0)", "google-pasta (>=0.1.1)", "grpcio (>=1.24.3,<2.0)", "h5py (>=2.9.0)", "keras (>=2.13.1rc0,<2.14)", "libclang (>=13.0.0)", "numpy (>=1.22)", "opt-einsum (>=2.3.2)", "packaging", "protobuf (>=3.20.3,!=4.21.0,!=4.21.1,!=4.21.2,!=4.21.3,!=4.21.4,!=4.21.5,<5.0.0dev)", "setuptools", "six (>=1.12.0)", "tensorboard (>=2.13,<2.14)", "tensorflow-estimator (>=2.13.0rc0,<2.14)", "tensorflow-io-gcs-filesystem (>=0.23.1) ; platform_machine != \"arm64\" or platform_system != \"Darwin\"", "termcolor (>=1.1.0)", "typing-extensions (>=3.6.6)", "wrapt (>=1.11.0,<1.15)"]}, "2.14.0.dev20230513": {"version": "2.14.0.dev20230513", "python_constraint": ">=3.8", "released_at": "2023-05-14T04:38:44+00:00", "yanked": false, "dependencies": ["absl-py (>=1.0.0)", "astunparse (>=1.6.0)", "flatbuffers (>=23.1.21)", "gast (>=0.2.1,<=0.4.0)", "google-pasta (>=0.1.1)", "grpcio (>=1.24.3,<2.0)", "h5py (>=2.9.0)", "keras (>=2.13.1rc0,<2.14)", "libclang (>=13.0.0)", "numpy (>=1.22)", "opt-einsum (>=2.3.2)", "packaging", "protobuf (>=3.20.3,!=4.21.0,!=4.21.1,!=4.21.2,!=4.21.3,!=4.21.4,!=4.21.5,<5.0.0dev)", "setuptools", "six (>=1.12.0)", "tensorboard (>=2.13,<2.14)", "tensorflow-estimator (>=2.13.0rc0,<2.14)", "tensorflow-io-gcs-filesystem (>=0.23.1) ; platform_machine != \"arm64\" or platform_system != \"Darwin\"", "termcolor (>=1.1.0)", "typing-extensions (>=3.6.6)", "wrapt (>=1.11.0,<1.15)"]}, "2.14.0.dev20230512": {"version": "2.14.0.dev20230512", "python_constraint": ">=3.8", "released_at": "2023-05-12T06:36:39+00:00", "yanked": false, "dependencies": ["absl-py (>=1.0.0)", "astunparse (>=1.6.0)", "flatbuffers (>=23.1.21)", "gast (>=0.2.1,<=0.4.0)", "google-pasta (>=0.1.1)", "grpcio (>=1.24.3,<2.0)", "h5py (>=2.9.0)", "keras (>=2.13.1rc0,<2.14)", "libclang (>=13.0.0)", "numpy (>=1.22)", "opt-einsum (>=2.3.2)", "packaging", "protobuf (>=3.20.3,!=4.21.0,!=4.21.1,!=4.21.2,!=4.21.3,!=4.21.4,!=4.21.5,<5.0.0dev)", "setuptools", "six (>=1.12.0)", "tensorboard (>=2.13,<2.14)", "tensorflow-estimator (>=2.13.0rc0,<2.14)", "tensorflow-io-gcs-filesystem (>=0.23.1) ; platform_machine != \"arm64\" or platform_system != \"Darwin\"", "termcolor (>=1.1.0)", "typing-extensions (>=3.6.6)", "wrapt (>=1.11.0,<1.15)"]}, "2.14.0.dev20230511": {"version": "2.14.0.dev20230511", "python_constraint": ">=3.8", "released_at": "2023-05-11T06:36:37+00:00", "yanked": false, "dependencies": ["absl-py (>=1.0.0)", "astunparse (>=1.6.0)", "flatbuffers (>=23.1.21)", "gast (>=0.2.1,<=0.4.0)", "google-pasta (>=0.1.1)", "grpcio (>=1.24.3,<2.0)", "h5py (>=2.9.0)", "keras (>=2.13.1rc0,<2.14)", "libclang (>=13.0.0)", "numpy (>=1.22)", "opt-einsum (>=2.3.2)", "packaging", "protobuf (>=3.20.3,!=4.21.0,!=4.21.1,!=4.21.2,!=4.21.3,!=4.21.4,!=4.21.5,<5.0.0dev)", "setuptools", "six (>=1.12.0)", "tensorboard (>=2.13,<2.14)", "tensorflow-estimator (>=2.13.0rc0,<2.14)", "tensorflow-io-gcs-filesystem (>=0.23.1) ; platform_machine != \"arm64\" or platform_system != \"Darwin\"", "termcolor (>=1.1.0)", "typing-extensions (>=3.6.6)", "wrapt (>=1.11.0,<1.15)"]}, "2.14.0.dev20230510": {"version": "2.14.0.dev20230510", "python_constraint": ">=3.8", "released_at": "2023-05-10T06:36:49+00:00", "yanked": false, "dependencies": ["absl-py (>=1.0.0)", "astunparse (>=1.6.0)", "flatbuffers (>=23.1.21)", "gast (>=0.2.1,<=0.4.0)", "google-pasta (>=0.1.1)", "grpcio (>=1.24.3,<2.0)", "h5py (>=2.9.0)", "keras (>=2.13.1rc0,<2.14)", "libclang (>=13.0.0)", "numpy (>=1.22)", "opt-einsum (>=2.3.2)", "packaging", "protobuf (>=3.20.3,!=4.21.0,!=4.21.1,!=4.21.2,!=4.21.3,!=4.21.4,!=4.21.5,<5.0.0dev)", "setuptools", "six (>=1.12.0)", "tensorboard (>=2.13,<2.14)", "tensorflow-estimator (>=2.13.0rc0,<2.14)", "tensorflow-io-gcs-filesystem (>=0.23.1) ; platform_machine != \"arm64\" or platform_system != \"Darwin\"", "termcolor (>=1.1.0)", "typing-extensions (>=3.6.6)", "wrapt (>=1.11.0,<1.15)"]}, "2.14.0.dev20230509": {"version": "2.14.0.dev20230509", "python_constraint": ">=3.8", "released_at": "2023-05-09T06:36:40+00:00", "yanked": false, "dependencies": ["absl-py (>=1.0.0)", "astunparse (>=1.6.0)", "flatbuffers (>=23.1.21)", "gast (>=0.2.1,<=0.4.0)", "google-pasta (>=0.1.1)", "grpcio (>=1.24.3,<2.0)", "h5py (>=2.9.0)", "keras (>=2.13.1rc0,<2.14)", "libclang (>=13.0.0)", "numpy (>=1.22)", "opt-einsum (>=2.3.2)", "packaging", "protobuf (>=3.20.3,!=4.21.0,!=4.21.1,!=4.21.2,!=4.21.3,!=4.21.4,!=4.21.5,<5.0.0dev)", "setuptools", "six (>=1.12.0)", "tensorboard (>=2.13,<2.14)", "tensorflow-estimator (>=2.13.0rc0,<2.14)", "tensorflow-io-gcs-filesystem (>=0.23.1) ; platform_machine != \"arm64\" or platform_system != \"Darwin\"", "termcolor (>=1.1.0)", "typing-extensions (>=3.6.6)", "wrapt (>=1.11.0,<1.15)"]}, "2.14.0.dev20230508": {"version": "2.14.0.dev20230508", "python_constraint": ">=3.8", "released_at": "2023-05-08T06:36:40+00:00", "yanked": false, "dependencies": ["absl-py (>=1.0.0)", "astunparse (>=1.6.0)", "flatbuffers (>=23.1.21)", "gast (>=0.2.1,<=0.4.0)", "google-pasta (>=0.1.1)", "grpcio (>=1.24.3,<2.0)", "h5py (>=2.9.0)", "keras (>=2.13.1rc0,<2.14)", "libclang (>=13.0.0)", "numpy (>=1.22)", "opt-einsum (>=2.3.2)", "packaging", "protobuf (>=3.20.3,!=4.21.0,!=4.21.1,!=4.21.2,!=4.21.3,!=4.21.4,!=4.21.5,<5.0.0dev)", "setuptools", "six (>=1.12.0)", "tensorboard (>=2.13,<2.14)", "tensorflow-estimator (>=2.13.0rc0,<2.14)", "tensorflow-io-gcs-filesystem (>=0.23.1) ; platform_machine != \"arm64\" or platform_system != \"Darwin\"", "termcolor (>=1.1.0)", "typing-extensions (>=3.6.6)", "wrapt (>=1.11.0,<1.15)"]}, "2.14.0.dev20230507": {"version": "2.14.0.dev20230507", "python_constraint": ">=3.8", "released_at": "2023-05-07T06:35:52+00:00", "yanked": false, "dependencies": ["absl-py (>=1.0.0)", "astunparse (>=1.6.0)", "flatbuffers (>=23.1.21)", "gast (>=0.2.1,<=0.4.0)", "google-pasta (>=0.1.1)", "grpcio (>=1.24.3,<2.0)", "h5py (>=2.9.0)", "keras (>=2.13.1rc0,<2.14)", "libclang (>=13.0.0)", "numpy (>=1.22)", "opt-einsum (>=2.3.2)", "packaging", "protobuf (>=3.20.3,!=4.21.0,!=4.21.1,!=4.21.2,!=4.21.3,!=4.21.4,!=4.21.5,<5.0.0dev)", "setuptools", "six (>=1.12.0)", "tensorboard (>=2.13,<2.14)", "tensorflow-estimator (>=2.13.0rc0,<2.14)", "tensorflow-io-gcs-filesystem (>=0.23.1) ; platform_machine != \"arm64\" or platform_system != \"Darwin\"", "termcolor (>=1.1.0)", "typing-extensions (>=3.6.6)", "wrapt (>=1.11.0,<1.15)"]}, "2.14.0.dev20230506": {"version": "2.14.0.dev20230506", "python_constraint": ">=3.8", "released_at": "2023-05-06T06:35:46+00:00", "yanked": false, "dependencies": ["absl-py (>=1.0.0)", "astunparse (>=1.6.0)", "flatbuffers (>=23.1.21)", "gast (>=0.2.1,<=0.4.0)", "google-pasta (>=0.1.1)", "grpcio (>=1.24.3,<2.0)", "h5py (>=2.9.0)", "keras (>=2.13.1rc0,<2.14)", "libclang (>=13.0.0)", "numpy (>=1.22)", "opt-einsum (>=2.3.2)", "packaging", "protobuf (>=3.20.3,!=4.21.0,!=4.21.1,!=4.21.2,!=4.21.3,!=4.21.4,!=4.21.5,<5.0.0dev)", "setuptools", "six (>=1.12.0)", "tensorboard (>=2.13,<2.14)", "tensorflow-estimator (>=2.13.0rc0,<2.14)", "tensorflow-io-gcs-filesystem (>=0.23.1) ; platform_machine != \"arm64\" or platform_system != \"Darwin\"", "termcolor (>=1.1.0)", "typing-extensions (>=3.6.6)", "wrapt (>=1.11.0,<1.15)"]}, "2.14.0.dev20230505": {"version": "2.14.0.dev20230505", "python_constraint": ">=3.8", "released_at": "2023-05-05T06:36:09+00:00", "yanked": false, "dependencies": ["absl-py (>=1.0.0)", "astunparse (>=1.6.0)", "flatbuffers (>=23.1.21)", "gast (>=0.2.1,<=0.4.0)", "google-pasta (>=0.1.1)", "grpcio (>=1.24.3,<2.0)", "h5py (>=2.9.0)", "keras (>=2.13.1rc0,<2.14)", "libclang (>=13.0.0)", "numpy (>=1.22)", "opt-einsum (>=2.3.2)", "packaging", "protobuf (>=3.20.3,!=4.21.0,!=4.21.1,!=4.21.2,!=4.21.3,!=4.21.4,!=4.21.5,<5.0.0dev)", "setuptools", "six (>=1.12.0)", "tensorboard (>=2.12,<2.13)", "tensorflow-estimator (>=2.13.0rc0,<2.14)", "tensorflow-io-gcs-filesystem (>=0.23.1) ; platform_machine != \"arm64\" or platform_system != \"Darwin\"", "termcolor (>=1.1.0)", "typing-extensions (>=3.6.6)", "wrapt (>=1.11.0,<1.15)"]}, "2.14.0.dev20230504": {"version": "2.14.0.dev20230504", "python_constraint": ">=3.8", "released_at": "2023-05-04T06:36:53+00:00", "yanked": false, "dependencies": ["absl-py (>=1.0.0)", "astunparse (>=1.6.0)", "flatbuffers (>=23.1.21)", "gast (>=0.2.1,<=0.4.0)", "google-pasta (>=0.1.1)", "grpcio (>=1.24.3,<2.0)", "h5py (>=2.9.0)", "keras (>=2.12.0rc0,<2.13)", "libclang (>=13.0.0)", "numpy (>=1.22)", "opt-einsum (>=2.3.2)", "packaging", "protobuf (>=3.20.3,!=4.21.0,!=4.21.1,!=4.21.2,!=4.21.3,!=4.21.4,!=4.21.5,<5.0.0dev)", "setuptools", "six (>=1.12.0)", "tensorboard (>=2.12,<2.13)", "tensorflow-estimator (>=2.12.0rc0,<2.13)", "tensorflow-io-gcs-filesystem (>=0.23.1) ; platform_machine != \"arm64\" or platform_system != \"Darwin\"", "termcolor (>=1.1.0)", "typing-extensions (>=3.6.6)", "wrapt (>=1.11.0,<1.15)"]}, "2.14.0.dev20230503": {"version": "2.14.0.dev20230503", "python_constraint": ">=3.8", "released_at": "2023-05-03T06:36:01+00:00", "yanked": false, "dependencies": ["absl-py (>=1.0.0)", "astunparse (>=1.6.0)", "flatbuffers (>=23.1.21)", "gast (>=0.2.1,<=0.4.0)", "google-pasta (>=0.1.1)", "grpcio (>=1.24.3,<2.0)", "h5py (>=2.9.0)", "keras (>=2.12.0rc0,<2.13)", "libclang (>=13.0.0)", "numpy (>=1.22)", "opt-einsum (>=2.3.2)", "packaging", "protobuf (>=3.20.3,!=4.21.0,!=4.21.1,!=4.21.2,!=4.21.3,!=4.21.4,!=4.21.5,<5.0.0dev)", "setuptools", "six (>=1.12.0)", "tensorboard (>=2.12,<2.13)", "tensorflow-estimator (>=2.12.0rc0,<2.13)", "tensorflow-io-gcs-filesystem (>=0.23.1) ; platform_machine != \"arm64\" or platform_system != \"Darwin\"", "termcolor (>=1.1.0)", "typing-extensions (>=3.6.6)", "wrapt (>=1.11.0,<1.15)"]}, "2.14.0.dev20230502": {"version": "2.14.0.dev20230502", "python_constraint": ">=3.8", "released_at": "2023-05-02T06:37:46+00:00", "yanked": false, "dependencies": ["absl-py (>=1.0.0)", "astunparse (>=1.6.0)", "flatbuffers (>=23.1.21)", "gast (>=0.2.1,<=0.4.0)", "google-pasta (>=0.1.1)", "grpcio (>=1.24.3,<2.0)", "h5py (>=2.9.0)", "keras (>=2.12.0rc0,<2.13)", "libclang (>=13.0.0)", "numpy (>=1.22)", "opt-einsum (>=2.3.2)", "packaging", "protobuf (>=3.20.3,!=4.21.0,!=4.21.1,!=4.21.2,!=4.21.3,!=4.21.4,!=4.21.5,<5.0.0dev)", "setuptools", "six (>=1.12.0)", "tensorboard (>=2.12,<2.13)", "tensorflow-estimator (>=2.12.0rc0,<2.13)", "tensorflow-io-gcs-filesystem (>=0.23.1) ; platform_machine != \"arm64\" or platform_system != \"Darwin\"", "termcolor (>=1.1.0)", "typing-extensions (>=3.6.6)", "wrapt (>=1.11.0,<1.15)"]}, "2.13.0.dev20230501": {"version": "2.13.0.dev20230501", "python_constraint": ">=3.8", "released_at": "2023-05-01T06:38:06+00:00", "yanked": false, "dependencies": ["absl-py (>=1.0.0)", "astunparse (>=1.6.0)", "flatbuffers (>=23.1.21)", "gast (>=0.2.1,<=0.4.0)", "google-pasta (>=0.1.1)", "grpcio (>=1.24.3,<2.0)", "h5py (>=2.9.0)", "keras (>=2.12.0rc0,<2.13)", "libclang (>=13.0.0)", "numpy (>=1.22)", "opt-einsum (>=2.3.2)", "packaging", "protobuf (>=3.20.3,!=4.21.0,!=4.21.1,!=4.21.2,!=4.21.3,!=4.21.4,!=4.21.5,<5.0.0dev)", "setuptools", "six (>=1.12.0)", "tensorboard (>=2.12,<2.13)", "tensorflow-estimator (>=2.12.0rc0,<2.13)", "tensorflow-io-gcs-filesystem (>=0.23.1) ; platform_machine != \"arm64\" or platform_system != \"Darwin\"", "termcolor (>=1.1.0)", "typing-extensions (>=3.6.6)", "wrapt (>=1.11.0,<1.15)"]}, "2.13.0.dev20230430": {"version": "2.13.0.dev20230430", "python_constraint": ">=3.8", "released_at": "2023-04-30T06:35:58+00:00", "yanked": false, "dependencies": ["absl-py (>=1.0.0)", "astunparse (>=1.6.0)", "flatbuffers (>=23.1.21)", "gast (>=0.2.1,<=0.4.0)", "google-pasta (>=0.1.1)", "grpcio (>=1.24.3,<2.0)", "h5py (>=2.9.0)", "keras (>=2.12.0rc0,<2.13)", "libclang (>=13.0.0)", "numpy (>=1.22)", "opt-einsum (>=2.3.2)", "packaging", "protobuf (>=3.20.3,!=4.21.0,!=4.21.1,!=4.21.2,!=4.21.3,!=4.21.4,!=4.21.5,<5.0.0dev)", "setuptools", "six (>=1.12.0)", "tensorboard (>=2.12,<2.13)", "tensorflow-estimator (>=2.12.0rc0,<2.13)", "tensorflow-io-gcs-filesystem (>=0.23.1) ; platform_machine != \"arm64\" or platform_system != \"Darwin\"", "termcolor (>=1.1.0)", "typing-extensions (>=3.6.6)", "wrapt (>=1.11.0,<1.15)"]}, "2.13.0.dev20230429": {"version": "2.13.0.dev20230429", "python_constraint": ">=3.8", "released_at": "2023-04-29T06:34:43+00:00", "yanked": false, "dependencies": ["absl-py (>=1.0.0)", "astunparse (>=1.6.0)", "flatbuffers (>=23.1.21)", "gast (>=0.2.1,<=0.4.0)", "google-pasta (>=0.1.1)", "grpcio (>=1.24.3,<2.0)", "h5py (>=2.9.0)", "keras (>=2.12.0rc0,<2.13)", "libclang (>=13.0.0)", "numpy (>=1.22)", "opt-einsum (>=2.3.2)", "packaging", "protobuf (>=3.20.3,!=4.21.0,!=4.21.1,!=4.21.2,!=4.21.3,!=4.21.4,!=4.21.5,<5.0.0dev)", "setuptools", "six (>=1.12.0)", "tensorboard (>=2.12,<2.13)", "tensorflow-estimator (>=2.12.0rc0,<2.13)", "tensorflow-io-gcs-filesystem (>=0.23.1) ; platform_machine != \"arm64\" or platform_system != \"Darwin\"", "termcolor (>=1.1.0)", "typing-extensions (>=3.6.6)", "wrapt (>=1.11.0,<1.15)"]}, "2.13.0.dev20230428": {"version": "2.13.0.dev20230428", "python_constraint": ">=3.8", "released_at": "2023-04-28T06:35:57+00:00", "yanked": false, "dependencies": ["absl-py (>=1.0.0)", "astunparse (>=1.6.0)", "flatbuffers (>=23.1.21)", "gast (>=0.2.1,<=0.4.0)", "google-pasta (>=0.1.1)", "grpcio (>=1.24.3,<2.0)", "h5py (>=2.9.0)", "keras (>=2.12.0rc0,<2.13)", "libclang (>=13.0.0)", "numpy (>=1.22)", "opt-einsum (>=2.3.2)", "packaging", "protobuf (>=3.20.3,!=4.21.0,!=4.21.1,!=4.21.2,!=4.21.3,!=4.21.4,!=4.21.5,<5.0.0dev)", "setuptools", "six (>=1.12.0)", "tensorboard (>=2.12,<2.13)", "tensorflow-estimator (>=2.12.0rc0,<2.13)", "tensorflow-io-gcs-filesystem (>=0.23.1) ; platform_machine != \"arm64\" or platform_system != \"Darwin\"", "termcolor (>=1.1.0)", "typing-extensions (>=3.6.6)", "wrapt (>=1.11.0,<1.15)"]}, "2.13.0.dev20230427": {"version": "2.13.0.dev20230427", "python_constraint": ">=3.8", "released_at": "2023-04-27T06:34:46+00:00", "yanked": false, "dependencies": ["absl-py (>=1.0.0)", "astunparse (>=1.6.0)", "flatbuffers (>=23.1.21)", "gast (>=0.2.1,<=0.4.0)", "google-pasta (>=0.1.1)", "grpcio (>=1.24.3,<2.0)", "h5py (>=2.9.0)", "keras (>=2.12.0rc0,<2.13)", "libclang (>=13.0.0)", "numpy (>=1.22)", "opt-einsum (>=2.3.2)", "packaging", "protobuf (>=3.20.3,!=4.21.0,!=4.21.1,!=4.21.2,!=4.21.3,!=4.21.4,!=4.21.5,<5.0.0dev)", "setuptools", "six (>=1.12.0)", "tensorboard (>=2.12,<2.13)", "tensorflow-estimator (>=2.12.0rc0,<2.13)", "tensorflow-io-gcs-filesystem (>=0.23.1) ; platform_machine != \"arm64\" or platform_system != \"Darwin\"", "termcolor (>=1.1.0)", "typing-extensions (>=3.6.6)", "wrapt (>=1.11.0,<1.15)"]}, "2.13.0.dev20230426": {"version": "2.13.0.dev20230426", "python_constraint": ">=3.8", "released_at": "2023-04-26T06:35:31+00:00", "yanked": false, "dependencies": ["absl-py (>=1.0.0)", "astunparse (>=1.6.0)", "flatbuffers (>=23.1.21)", "gast (>=0.2.1,<=0.4.0)", "google-pasta (>=0.1.1)", "grpcio (>=1.24.3,<2.0)", "h5py (>=2.9.0)", "keras (>=2.12.0rc0,<2.13)", "libclang (>=13.0.0)", "numpy (>=1.22)", "opt-einsum (>=2.3.2)", "packaging", "protobuf (>=3.20.3,!=4.21.0,!=4.21.1,!=4.21.2,!=4.21.3,!=4.21.4,!=4.21.5,<5.0.0dev)", "setuptools", "six (>=1.12.0)", "tensorboard (>=2.12,<2.13)", "tensorflow-estimator (>=2.12.0rc0,<2.13)", "tensorflow-io-gcs-filesystem (>=0.23.1) ; platform_machine != \"arm64\" or platform_system != \"Darwin\"", "termcolor (>=1.1.0)", "typing-extensions (>=3.6.6)", "wrapt (>=1.11.0,<1.15)"]}, "2.13.0.dev20230425": {"version": "2.13.0.dev20230425", "python_constraint": ">=3.8", "released_at": "2023-04-25T06:34:30+00:00", "yanked": false, "dependencies": ["absl-py (>=1.0.0)", "astunparse (>=1.6.0)", "flatbuffers (>=23.1.21)", "gast (>=0.2.1,<=0.4.0)", "google-pasta (>=0.1.1)", "grpcio (>=1.24.3,<2.0)", "h5py (>=2.9.0)", "keras (>=2.12.0rc0,<2.13)", "libclang (>=13.0.0)", "numpy (>=1.22)", "opt-einsum (>=2.3.2)", "packaging", "protobuf (>=3.20.3,!=4.21.0,!=4.21.1,!=4.21.2,!=4.21.3,!=4.21.4,!=4.21.5,<5.0.0dev)", "setuptools", "six (>=1.12.0)", "tensorboard (>=2.12,<2.13)", "tensorflow-estimator (>=2.12.0rc0,<2.13)", "tensorflow-io-gcs-filesystem (>=0.23.1) ; platform_machine != \"arm64\" or platform_system != \"Darwin\"", "termcolor (>=1.1.0)", "typing-extensions (>=3.6.6)", "wrapt (>=1.11.0,<1.15)"]}, "2.13.0.dev20230424": {"version": "2.13.0.dev20230424", "python_constraint": ">=3.8", "released_at": "2023-04-24T06:36:15+00:00", "yanked": false, "dependencies": ["absl-py (>=1.0.0)", "astunparse (>=1.6.0)", "flatbuffers (>=23.1.21)", "gast (>=0.2.1,<=0.4.0)", "google-pasta (>=0.1.1)", "grpcio (>=1.24.3,<2.0)", "h5py (>=2.9.0)", "keras (>=2.12.0rc0,<2.13)", "libclang (>=13.0.0)", "numpy (>=1.22)", "opt-einsum (>=2.3.2)", "packaging", "protobuf (>=3.20.3,!=4.21.0,!=4.21.1,!=4.21.2,!=4.21.3,!=4.21.4,!=4.21.5,<5.0.0dev)", "setuptools", "six (>=1.12.0)", "tensorboard (>=2.12,<2.13)", "tensorflow-estimator (>=2.12.0rc0,<2.13)", "tensorflow-io-gcs-filesystem (>=0.23.1) ; platform_machine != \"arm64\" or platform_system != \"Darwin\"", "termcolor (>=1.1.0)", "typing-extensions (>=3.6.6)", "wrapt (>=1.11.0,<1.15)"]}, "2.13.0.dev20230423": {"version": "2.13.0.dev20230423", "python_constraint": ">=3.8", "released_at": "2023-04-23T06:35:13+00:00", "yanked": false, "dependencies": ["absl-py (>=1.0.0)", "astunparse (>=1.6.0)", "flatbuffers (>=23.1.21)", "gast (>=0.2.1,<=0.4.0)", "google-pasta (>=0.1.1)", "grpcio (>=1.24.3,<2.0)", "h5py (>=2.9.0)", "keras (>=2.12.0rc0,<2.13)", "libclang (>=13.0.0)", "numpy (>=1.22)", "opt-einsum (>=2.3.2)", "packaging", "protobuf (>=3.20.3,!=4.21.0,!=4.21.1,!=4.21.2,!=4.21.3,!=4.21.4,!=4.21.5,<5.0.0dev)", "setuptools", "six (>=1.12.0)", "tensorboard (>=2.12,<2.13)", "tensorflow-estimator (>=2.12.0rc0,<2.13)", "tensorflow-io-gcs-filesystem (>=0.23.1) ; platform_machine != \"arm64\" or platform_system != \"Darwin\"", "termcolor (>=1.1.0)", "typing-extensions (>=3.6.6)", "wrapt (>=1.11.0,<1.15)"]}, "2.13.0.dev20230422": {"version": "2.13.0.dev20230422", "python_constraint": ">=3.8", "released_at": "2023-04-22T06:35:20+00:00", "yanked": false, "dependencies": ["absl-py (>=1.0.0)", "astunparse (>=1.6.0)", "flatbuffers (>=23.1.21)", "gast (>=0.2.1,<=0.4.0)", "google-pasta (>=0.1.1)", "grpcio (>=1.24.3,<2.0)", "h5py (>=2.9.0)", "keras (>=2.12.0rc0,<2.13)", "libclang (>=13.0.0)", "numpy (>=1.22)", "opt-einsum (>=2.3.2)", "packaging", "protobuf (>=3.20.3,!=4.21.0,!=4.21.1,!=4.21.2,!=4.21.3,!=4.21.4,!=4.21.5,<5.0.0dev)", "setuptools", "six (>=1.12.0)", "tensorboard (>=2.12,<2.13)", "tensorflow-estimator (>=2.12.0rc0,<2.13)", "tensorflow-io-gcs-filesystem (>=0.23.1) ; platform_machine != \"arm64\" or platform_system != \"Darwin\"", "termcolor (>=1.1.0)", "typing-extensions (>=3.6.6)", "wrapt (>=1.11.0,<1.15)"]}, "2.13.0.dev20230421": {"version": "2.13.0.dev20230421", "python_constraint": ">=3.8", "released_at": "2023-04-21T08:03:30+00:00", "yanked": false, "dependencies": ["absl-py (>=1.0.0)", "astunparse (>=1.6.0)", "flatbuffers (>=23.1.21)", "gast (>=0.2.1,<=0.4.0)", "google-pasta (>=0.1.1)", "grpcio (>=1.24.3,<2.0)", "h5py (>=2.9.0)", "keras (>=2.12.0rc0,<2.13)", "libclang (>=13.0.0)", "numpy (>=1.22)", "opt-einsum (>=2.3.2)", "packaging", "protobuf (>=3.20.3,!=4.21.0,!=4.21.1,!=4.21.2,!=4.21.3,!=4.21.4,!=4.21.5,<5.0.0dev)", "setuptools", "six (>=1.12.0)", "tensorboard (>=2.12,<2.13)", "tensorflow-estimator (>=2.12.0rc0,<2.13)", "tensorflow-io-gcs-filesystem (>=0.23.1) ; platform_machine != \"arm64\" or platform_system != \"Darwin\"", "termcolor (>=1.1.0)", "typing-extensions (>=3.6.6)", "wrapt (>=1.11.0,<1.15)"]}, "2.13.0.dev20230420": {"version": "2.13.0.dev20230420", "python_constraint": ">=3.8", "released_at": "2023-04-20T08:03:16+00:00", "yanked": false, "dependencies": ["absl-py (>=1.0.0)", "astunparse (>=1.6.0)", "flatbuffers (>=23.1.21)", "gast (>=0.2.1,<=0.4.0)", "google-pasta (>=0.1.1)", "grpcio (>=1.24.3,<2.0)", "h5py (>=2.9.0)", "keras (>=2.12.0rc0,<2.13)", "libclang (>=13.0.0)", "numpy (>=1.22)", "opt-einsum (>=2.3.2)", "packaging", "protobuf (>=3.20.3,!=4.21.0,!=4.21.1,!=4.21.2,!=4.21.3,!=4.21.4,!=4.21.5,<5.0.0dev)", "setuptools", "six (>=1.12.0)", "tensorboard (>=2.12,<2.13)", "tensorflow-estimator (>=2.12.0rc0,<2.13)", "tensorflow-io-gcs-filesystem (>=0.23.1) ; platform_machine != \"arm64\" or platform_system != \"Darwin\"", "termcolor (>=1.1.0)", "typing-extensions (>=3.6.6)", "wrapt (>=1.11.0,<1.15)"]}, "2.13.0.dev20230419": {"version": "2.13.0.dev20230419", "python_constraint": ">=3.8", "released_at": "2023-04-19T07:37:21+00:00", "yanked": false, "dependencies": ["absl-py (>=1.0.0)", "astunparse (>=1.6.0)", "flatbuffers (>=23.1.21)", "gast (>=0.2.1,<=0.4.0)", "google-pasta (>=0.1.1)", "grpcio (>=1.24.3,<2.0)", "h5py (>=2.9.0)", "keras (>=2.12.0rc0,<2.13)", "libclang (>=13.0.0)", "numpy (>=1.22)", "opt-einsum (>=2.3.2)", "packaging", "protobuf (>=3.20.3,!=4.21.0,!=4.21.1,!=4.21.2,!=4.21.3,!=4.21.4,!=4.21.5,<5.0.0dev)", "setuptools", "six (>=1.12.0)", "tensorboard (>=2.12,<2.13)", "tensorflow-estimator (>=2.12.0rc0,<2.13)", "tensorflow-io-gcs-filesystem (>=0.23.1) ; platform_machine != \"arm64\" or platform_system != \"Darwin\"", "termcolor (>=1.1.0)", "typing-extensions (>=3.6.6)", "wrapt (>=1.11.0,<1.15)"]}, "2.13.0.dev20230418": {"version": "2.13.0.dev20230418", "python_constraint": ">=3.8", "released_at": "2023-04-18T10:02:33+00:00", "yanked": false, "dependencies": ["absl-py (>=1.0.0)", "astunparse (>=1.6.0)", "flatbuffers (>=23.1.21)", "gast (>=0.2.1,<=0.4.0)", "google-pasta (>=0.1.1)", "grpcio (>=1.24.3,<2.0)", "h5py (>=2.9.0)", "keras (>=2.12.0rc0,<2.13)", "libclang (>=13.0.0)", "numpy (>=1.22,<1.24)", "opt-einsum (>=2.3.2)", "packaging", "protobuf (>=3.20.3,!=4.21.0,!=4.21.1,!=4.21.2,!=4.21.3,!=4.21.4,!=4.21.5,<5.0.0dev)", "setuptools", "six (>=1.12.0)", "tensorboard (>=2.12,<2.13)", "tensorflow-estimator (>=2.12.0rc0,<2.13)", "tensorflow-io-gcs-filesystem (>=0.23.1) ; platform_machine != \"arm64\" or platform_system != \"Darwin\"", "termcolor (>=1.1.0)", "typing-extensions (>=3.6.6)", "wrapt (>=1.11.0,<1.15)"]}, "2.13.0.dev20230417": {"version": "2.13.0.dev20230417", "python_constraint": ">=3.8", "released_at": "2023-04-17T22:30:25+00:00", "yanked": false, "dependencies": ["absl-py (>=1.0.0)", "astunparse (>=1.6.0)", "flatbuffers (>=23.1.21)", "gast (>=0.2.1,<=0.4.0)", "google-pasta (>=0.1.1)", "grpcio (>=1.24.3,<2.0)", "h5py (>=2.9.0)", "keras (>=2.12.0rc0,<2.13)", "libclang (>=13.0.0)", "numpy (>=1.22,<1.24)", "opt-einsum (>=2.3.2)", "packaging", "protobuf (>=3.20.3,!=4.21.0,!=4.21.1,!=4.21.2,!=4.21.3,!=4.21.4,!=4.21.5,<5.0.0dev)", "setuptools", "six (>=1.12.0)", "tensorboard (>=2.12,<2.13)", "tensorflow-estimator (>=2.12.0rc0,<2.13)", "tensorflow-io-gcs-filesystem (>=0.23.1) ; platform_machine != \"arm64\" or platform_system != \"Darwin\"", "termcolor (>=1.1.0)", "typing-extensions (>=3.6.6)", "wrapt (>=1.11.0,<1.15)"]}, "2.13.0.dev20230413": {"version": "2.13.0.dev20230413", "python_constraint": ">=3.8", "released_at": "2023-04-13T07:46:26+00:00", "yanked": false, "dependencies": ["absl-py (>=1.0.0)", "astunparse (>=1.6.0)", "flatbuffers (>=23.1.21)", "gast (>=0.2.1,<=0.4.0)", "google-pasta (>=0.1.1)", "grpcio (>=1.24.3,<2.0)", "h5py (>=2.9.0)", "keras (>=2.12.0rc0,<2.13)", "libclang (>=13.0.0)", "numpy (>=1.22,<1.24)", "opt-einsum (>=2.3.2)", "packaging", "protobuf (>=3.20.3,!=4.21.0,!=4.21.1,!=4.21.2,!=4.21.3,!=4.21.4,!=4.21.5,<5.0.0dev)", "setuptools", "six (>=1.12.0)", "tensorboard (>=2.12,<2.13)", "tensorflow-estimator (>=2.12.0rc0,<2.13)", "tensorflow-io-gcs-filesystem (>=0.23.1) ; platform_machine != \"arm64\" or platform_system != \"Darwin\"", "termcolor (>=1.1.0)", "typing-extensions (>=3.6.6)", "wrapt (>=1.11.0,<1.15)"]}, "2.13.0.dev20230412": {"version": "2.13.0.dev20230412", "python_constraint": ">=3.8", "released_at": "2023-04-12T07:46:34+00:00", "yanked": false, "dependencies": ["absl-py (>=1.0.0)", "astunparse (>=1.6.0)", "flatbuffers (>=23.1.21)", "gast (>=0.2.1,<=0.4.0)", "google-pasta (>=0.1.1)", "grpcio (>=1.24.3,<2.0)", "h5py (>=2.9.0)", "keras (>=2.12.0rc0,<2.13)", "libclang (>=13.0.0)", "numpy (>=1.22,<1.24)", "opt-einsum (>=2.3.2)", "packaging", "protobuf (>=3.20.3,!=4.21.0,!=4.21.1,!=4.21.2,!=4.21.3,!=4.21.4,!=4.21.5,<5.0.0dev)", "setuptools", "six (>=1.12.0)", "tensorboard (>=2.12,<2.13)", "tensorflow-estimator (>=2.12.0rc0,<2.13)", "tensorflow-io-gcs-filesystem (>=0.23.1) ; platform_machine != \"arm64\" or platform_system != \"Darwin\"", "termcolor (>=1.1.0)", "typing-extensions (>=3.6.6)", "wrapt (>=1.11.0,<1.15)"]}, "2.13.0.dev20230411": {"version": "2.13.0.dev20230411", "python_constraint": ">=3.8", "released_at": "2023-04-11T07:41:34+00:00", "yanked": false, "dependencies": ["absl-py (>=1.0.0)", "astunparse (>=1.6.0)", "flatbuffers (>=23.1.21)", "gast (>=0.2.1,<=0.4.0)", "google-pasta (>=0.1.1)", "grpcio (>=1.24.3,<2.0)", "h5py (>=2.9.0)", "keras (>=2.12.0rc0,<2.13)", "libclang (>=13.0.0)", "numpy (>=1.22,<1.24)", "opt-einsum (>=2.3.2)", "packaging", "protobuf (>=3.20.3,!=4.21.0,!=4.21.1,!=4.21.2,!=4.21.3,!=4.21.4,!=4.21.5,<5.0.0dev)", "setuptools", "six (>=1.12.0)", "tensorboard (>=2.12,<2.13)", "tensorflow-estimator (>=2.12.0rc0,<2.13)", "tensorflow-io-gcs-filesystem (>=0.23.1) ; platform_machine != \"arm64\" or platform_system != \"Darwin\"", "termcolor (>=1.1.0)", "typing-extensions (>=3.6.6)", "wrapt (>=1.11.0,<1.15)"]}, "2.13.0.dev20230410": {"version": "2.13.0.dev20230410", "python_constraint": ">=3.8", "released_at": "2023-04-10T07:39:46+00:00", "yanked": false, "dependencies": ["absl-py (>=1.0.0)", "astunparse (>=1.6.0)", "flatbuffers (>=23.1.21)", "gast (>=0.2.1,<=0.4.0)", "google-pasta (>=0.1.1)", "grpcio (>=1.24.3,<2.0)", "h5py (>=2.9.0)", "keras (>=2.12.0rc0,<2.13)", "libclang (>=13.0.0)", "numpy (>=1.22,<1.24)", "opt-einsum (>=2.3.2)", "packaging", "protobuf (>=3.20.3,!=4.21.0,!=4.21.1,!=4.21.2,!=4.21.3,!=4.21.4,!=4.21.5,<5.0.0dev)", "setuptools", "six (>=1.12.0)", "tensorboard (>=2.12,<2.13)", "tensorflow-estimator (>=2.12.0rc0,<2.13)", "tensorflow-io-gcs-filesystem (>=0.23.1) ; platform_machine != \"arm64\" or platform_system != \"Darwin\"", "termcolor (>=1.1.0)", "typing-extensions (>=3.6.6)", "wrapt (>=1.11.0,<1.15)"]}, "2.13.0.dev20230409": {"version": "2.13.0.dev20230409", "python_constraint": ">=3.8", "released_at": "2023-04-09T07:42:42+00:00", "yanked": false, "dependencies": ["absl-py (>=1.0.0)", "astunparse (>=1.6.0)", "flatbuffers (>=23.1.21)", "gast (>=0.2.1,<=0.4.0)", "google-pasta (>=0.1.1)", "grpcio (>=1.24.3,<2.0)", "h5py (>=2.9.0)", "keras (>=2.12.0rc0,<2.13)", "libclang (>=13.0.0)", "numpy (>=1.22,<1.24)", "opt-einsum (>=2.3.2)", "packaging", "protobuf (>=3.20.3,!=4.21.0,!=4.21.1,!=4.21.2,!=4.21.3,!=4.21.4,!=4.21.5,<5.0.0dev)", "setuptools", "six (>=1.12.0)", "tensorboard (>=2.12,<2.13)", "tensorflow-estimator (>=2.12.0rc0,<2.13)", "tensorflow-io-gcs-filesystem (>=0.23.1) ; platform_machine != \"arm64\" or platform_system != \"Darwin\"", "termcolor (>=1.1.0)", "typing-extensions (>=3.6.6)", "wrapt (>=1.11.0,<1.15)"]}, "2.13.0.dev20230408": {"version": "2.13.0.dev20230408", "python_constraint": ">=3.8", "released_at": "2023-04-08T07:42:25+00:00", "yanked": false, "dependencies": ["absl-py (>=1.0.0)", "astunparse (>=1.6.0)", "flatbuffers (>=23.1.21)", "gast (>=0.2.1,<=0.4.0)", "google-pasta (>=0.1.1)", "grpcio (>=1.24.3,<2.0)", "h5py (>=2.9.0)", "jax (>=0.3.15)", "keras (>=2.12.0rc0,<2.13)", "libclang (>=13.0.0)", "numpy (>=1.22,<1.24)", "opt-einsum (>=2.3.2)", "packaging", "protobuf (>=3.20.3,!=4.21.0,!=4.21.1,!=4.21.2,!=4.21.3,!=4.21.4,!=4.21.5,<5.0.0dev)", "setuptools", "six (>=1.12.0)", "tensorboard (>=2.12,<2.13)", "tensorflow-estimator (>=2.12.0rc0,<2.13)", "tensorflow-io-gcs-filesystem (>=0.23.1) ; platform_machine != \"arm64\" or platform_system != \"Darwin\"", "termcolor (>=1.1.0)", "typing-extensions (>=3.6.6)", "wrapt (>=1.11.0,<1.15)"]}, "2.13.0.dev20230406": {"version": "2.13.0.dev20230406", "python_constraint": ">=3.8", "released_at": "2023-04-06T07:35:57+00:00", "yanked": false, "dependencies": ["absl-py (>=1.0.0)", "astunparse (>=1.6.0)", "flatbuffers (>=23.1.21)", "gast (>=0.2.1,<=0.4.0)", "google-pasta (>=0.1.1)", "grpcio (>=1.24.3,<2.0)", "h5py (>=2.9.0)", "jax (>=0.3.15)", "keras (>=2.12.0rc0,<2.13)", "libclang (>=13.0.0)", "numpy (>=1.22,<1.24)", "opt-einsum (>=2.3.2)", "packaging", "protobuf (>=3.20.3,!=4.21.0,!=4.21.1,!=4.21.2,!=4.21.3,!=4.21.4,!=4.21.5,<5.0.0dev)", "setuptools", "six (>=1.12.0)", "tensorboard (>=2.12,<2.13)", "tensorflow-estimator (>=2.12.0rc0,<2.13)", "tensorflow-io-gcs-filesystem (>=0.23.1) ; platform_machine != \"arm64\" or platform_system != \"Darwin\"", "termcolor (>=1.1.0)", "typing-extensions (>=3.6.6)", "wrapt (>=1.11.0,<1.15)"]}, "2.13.0.dev20230405": {"version": "2.13.0.dev20230405", "python_constraint": ">=3.8", "released_at": "2023-04-05T12:31:10+00:00", "yanked": false, "dependencies": ["absl-py (>=1.0.0)", "astunparse (>=1.6.0)", "flatbuffers (>=23.1.21)", "gast (>=0.2.1,<=0.4.0)", "google-pasta (>=0.1.1)", "grpcio (>=1.24.3,<2.0)", "h5py (>=2.9.0)", "jax (>=0.3.15)", "keras (>=2.12.0rc0,<2.13)", "libclang (>=13.0.0)", "numpy (>=1.22,<1.24)", "opt-einsum (>=2.3.2)", "packaging", "protobuf (>=3.20.3,!=4.21.0,!=4.21.1,!=4.21.2,!=4.21.3,!=4.21.4,!=4.21.5,<5.0.0dev)", "setuptools", "six (>=1.12.0)", "tensorboard (>=2.12,<2.13)", "tensorflow-estimator (>=2.12.0rc0,<2.13)", "tensorflow-io-gcs-filesystem (>=0.23.1) ; platform_machine != \"arm64\" or platform_system != \"Darwin\"", "termcolor (>=1.1.0)", "typing-extensions (>=3.6.6)", "wrapt (>=1.11.0,<1.15)"]}, "2.13.0.dev20230404": {"version": "2.13.0.dev20230404", "python_constraint": ">=3.8", "released_at": "2023-04-04T17:12:15+00:00", "yanked": false, "dependencies": ["absl-py (>=1.0.0)", "astunparse (>=1.6.0)", "flatbuffers (>=23.1.21)", "gast (>=0.2.1,<=0.4.0)", "google-pasta (>=0.1.1)", "grpcio (>=1.24.3,<2.0)", "h5py (>=2.9.0)", "jax (>=0.3.15)", "keras (>=2.12.0rc0,<2.13)", "libclang (>=13.0.0)", "numpy (>=1.22,<1.24)", "opt-einsum (>=2.3.2)", "packaging", "protobuf (>=3.20.3,!=4.21.0,!=4.21.1,!=4.21.2,!=4.21.3,!=4.21.4,!=4.21.5,<5.0.0dev)", "setuptools", "six (>=1.12.0)", "tensorboard (>=2.12,<2.13)", "tensorflow-estimator (>=2.12.0rc0,<2.13)", "tensorflow-io-gcs-filesystem (>=0.23.1) ; platform_machine != \"arm64\" or platform_system != \"Darwin\"", "termcolor (>=1.1.0)", "typing-extensions (>=3.6.6)", "wrapt (>=1.11.0,<1.15)"]}, "2.13.0.dev20230331": {"version": "2.13.0.dev20230331", "python_constraint": ">=3.8", "released_at": "2023-03-31T17:36:46+00:00", "yanked": false, "dependencies": ["absl-py (>=1.0.0)", "astunparse (>=1.6.0)", "flatbuffers (>=23.1.21)", "gast (>=0.2.1,<=0.4.0)", "google-pasta (>=0.1.1)", "grpcio (>=1.24.3,<2.0)", "h5py (>=2.9.0)", "jax (>=0.3.15)", "keras (>=2.12.0rc0,<2.13)", "libclang (>=13.0.0)", "numpy (>=1.22,<1.24)", "opt-einsum (>=2.3.2)", "packaging", "protobuf (>=3.20.3,!=4.21.0,!=4.21.1,!=4.21.2,!=4.21.3,!=4.21.4,!=4.21.5,<5.0.0dev)", "setuptools", "six (>=1.12.0)", "tensorboard (>=2.12,<2.13)", "tensorflow-estimator (>=2.12.0rc0,<2.13)", "tensorflow-io-gcs-filesystem (>=0.23.1) ; platform_machine != \"arm64\" or platform_system != \"Darwin\"", "termcolor (>=1.1.0)", "typing-extensions (>=3.6.6)", "wrapt (>=1.11.0,<1.15)"]}, "2.13.0.dev20230330": {"version": "2.13.0.dev20230330", "python_constraint": ">=3.8", "released_at": "2023-03-30T17:46:56+00:00", "yanked": false, "dependencies": ["absl-py (>=1.0.0)", "astunparse (>=1.6.0)", "flatbuffers (>=23.1.20)", "gast (>=0.2.1,<=0.4.0)", "google-pasta (>=0.1.1)", "grpcio (>=1.24.3,<2.0)", "h5py (>=2.9.0)", "jax (>=0.3.15)", "keras (>=2.12.0rc0,<2.13)", "libclang (>=13.0.0)", "numpy (>=1.22,<1.24)", "opt-einsum (>=2.3.2)", "packaging", "protobuf (>=3.20.3,!=4.21.0,!=4.21.1,!=4.21.2,!=4.21.3,!=4.21.4,!=4.21.5,<5.0.0dev)", "setuptools", "six (>=1.12.0)", "tensorboard (>=2.12,<2.13)", "tensorflow-estimator (>=2.12.0rc0,<2.13)", "tensorflow-io-gcs-filesystem (>=0.23.1) ; platform_machine != \"arm64\" or platform_system != \"Darwin\"", "termcolor (>=1.1.0)", "typing-extensions (>=3.6.6)", "wrapt (>=1.11.0,<1.15)"]}, "2.13.0.dev20230329": {"version": "2.13.0.dev20230329", "python_constraint": ">=3.8", "released_at": "2023-03-29T22:36:52+00:00", "yanked": false, "dependencies": ["absl-py (>=1.0.0)", "astunparse (>=1.6.0)", "flatbuffers (>=23.1.20)", "gast (>=0.2.1,<=0.4.0)", "google-pasta (>=0.1.1)", "grpcio (>=1.24.3,<2.0)", "h5py (>=2.9.0)", "jax (>=0.3.15)", "keras (>=2.12.0rc0,<2.13)", "libclang (>=13.0.0)", "numpy (>=1.22,<1.24)", "opt-einsum (>=2.3.2)", "packaging", "protobuf (>=3.20.3,!=4.21.0,!=4.21.1,!=4.21.2,!=4.21.3,!=4.21.4,!=4.21.5,<5.0.0dev)", "setuptools", "six (>=1.12.0)", "tensorboard (>=2.12,<2.13)", "tensorflow-estimator (>=2.12.0rc0,<2.13)", "tensorflow-io-gcs-filesystem (>=0.23.1) ; platform_machine != \"arm64\" or platform_system != \"Darwin\"", "termcolor (>=1.1.0)", "typing-extensions (>=3.6.6)", "wrapt (>=1.11.0,<1.15)"]}, "2.13.0.dev20230325": {"version": "2.13.0.dev20230325", "python_constraint": ">=3.8", "released_at": "2023-03-26T00:02:19+00:00", "yanked": false, "dependencies": ["absl-py (>=1.0.0)", "astunparse (>=1.6.0)", "flatbuffers (>=23.1.20)", "gast (>=0.2.1,<=0.4.0)", "google-pasta (>=0.1.1)", "grpcio (>=1.24.3,<2.0)", "h5py (>=2.9.0)", "jax (>=0.3.15)", "keras (>=2.12.0rc0,<2.13)", "libclang (>=13.0.0)", "numpy (>=1.22,<1.24)", "opt-einsum (>=2.3.2)", "packaging", "protobuf (>=3.20.3,!=4.21.0,!=4.21.1,!=4.21.2,!=4.21.3,!=4.21.4,!=4.21.5,<5.0.0dev)", "setuptools", "six (>=1.12.0)", "tensorboard (>=2.12,<2.13)", "tensorflow-estimator (>=2.12.0rc0,<2.13)", "tensorflow-io-gcs-filesystem (>=0.23.1) ; platform_machine != \"arm64\" or platform_system != \"Darwin\"", "termcolor (>=1.1.0)", "typing-extensions (>=3.6.6)", "wrapt (>=1.11.0,<1.15)"]}, "2.13.0.dev20230324": {"version": "2.13.0.dev20230324", "python_constraint": ">=3.8", "released_at": "2023-03-24T18:29:32+00:00", "yanked": false, "dependencies": ["absl-py (>=1.0.0)", "astunparse (>=1.6.0)", "flatbuffers (>=2.0)", "gast (>=0.2.1,<=0.4.0)", "google-pasta (>=0.1.1)", "grpcio (>=1.24.3,<2.0)", "h5py (>=2.9.0)", "jax (>=0.3.15)", "keras (>=2.12.0rc0,<2.13)", "libclang (>=13.0.0)", "numpy (>=1.22,<1.24)", "opt-einsum (>=2.3.2)", "packaging", "protobuf (>=3.20.3,!=4.21.0,!=4.21.1,!=4.21.2,!=4.21.3,!=4.21.4,!=4.21.5,<5.0.0dev)", "setuptools", "six (>=1.12.0)", "tensorboard (>=2.12,<2.13)", "tensorflow-estimator (>=2.12.0rc0,<2.13)", "tensorflow-io-gcs-filesystem (>=0.23.1) ; platform_machine != \"arm64\" or platform_system != \"Darwin\"", "termcolor (>=1.1.0)", "typing-extensions (>=3.6.6)", "wrapt (>=1.11.0,<1.15)"]}, "2.13.0.dev20230323": {"version": "2.13.0.dev20230323", "python_constraint": ">=3.8", "released_at": "2023-03-23T11:40:43+00:00", "yanked": false, "dependencies": ["absl-py (>=1.0.0)", "astunparse (>=1.6.0)", "flatbuffers (>=2.0)", "gast (>=0.2.1,<=0.4.0)", "google-pasta (>=0.1.1)", "grpcio (>=1.24.3,<2.0)", "h5py (>=2.9.0)", "jax (>=0.3.15)", "keras (>=2.12.0rc0,<2.13)", "libclang (>=13.0.0)", "numpy (>=1.22,<1.24)", "opt-einsum (>=2.3.2)", "packaging", "protobuf (>=3.20.3,!=4.21.0,!=4.21.1,!=4.21.2,!=4.21.3,!=4.21.4,!=4.21.5,<5.0.0dev)", "setuptools", "six (>=1.12.0)", "tensorboard (>=2.12,<2.13)", "tensorflow-estimator (>=2.12.0rc0,<2.13)", "tensorflow-io-gcs-filesystem (>=0.23.1) ; platform_machine != \"arm64\" or platform_system != \"Darwin\"", "termcolor (>=1.1.0)", "typing-extensions (>=3.6.6)", "wrapt (>=1.11.0,<1.15)"]}, "2.13.0.dev20230322": {"version": "2.13.0.dev20230322", "python_constraint": ">=3.8", "released_at": "2023-03-22T16:13:18+00:00", "yanked": false, "dependencies": ["absl-py (>=1.0.0)", "astunparse (>=1.6.0)", "flatbuffers (>=2.0)", "gast (>=0.2.1,<=0.4.0)", "google-pasta (>=0.1.1)", "grpcio (>=1.24.3,<2.0)", "h5py (>=2.9.0)", "jax (>=0.3.15)", "keras (>=2.12.0rc0,<2.13)", "libclang (>=13.0.0)", "numpy (>=1.22,<1.24)", "opt-einsum (>=2.3.2)", "packaging", "protobuf (>=3.20.3,!=4.21.0,!=4.21.1,!=4.21.2,!=4.21.3,!=4.21.4,!=4.21.5,<5.0.0dev)", "setuptools", "six (>=1.12.0)", "tensorboard (>=2.12,<2.13)", "tensorflow-estimator (>=2.12.0rc0,<2.13)", "tensorflow-io-gcs-filesystem (>=0.23.1) ; platform_machine != \"arm64\" or platform_system != \"Darwin\"", "termcolor (>=1.1.0)", "typing-extensions (>=3.6.6)", "wrapt (>=1.11.0,<1.15)"]}, "2.13.0.dev20230321": {"version": "2.13.0.dev20230321", "python_constraint": ">=3.8", "released_at": "2023-03-21T16:00:06+00:00", "yanked": false, "dependencies": ["absl-py (>=1.0.0)", "astunparse (>=1.6.0)", "flatbuffers (>=2.0)", "gast (>=0.2.1,<=0.4.0)", "google-pasta (>=0.1.1)", "grpcio (>=1.24.3,<2.0)", "h5py (>=2.9.0)", "jax (>=0.3.15)", "keras (>=2.12.0rc0,<2.13)", "libclang (>=13.0.0)", "numpy (>=1.22,<1.24)", "opt-einsum (>=2.3.2)", "packaging", "protobuf (>=3.20.3,!=4.21.0,!=4.21.1,!=4.21.2,!=4.21.3,!=4.21.4,!=4.21.5,<5.0.0dev)", "setuptools", "six (>=1.12.0)", "tensorboard (>=2.12,<2.13)", "tensorflow-estimator (>=2.12.0rc0,<2.13)", "tensorflow-io-gcs-filesystem (>=0.23.1) ; platform_machine != \"arm64\" or platform_system != \"Darwin\"", "termcolor (>=1.1.0)", "typing-extensions (>=3.6.6)", "wrapt (>=1.11.0,<1.15)"]}, "2.13.0.dev20230320": {"version": "2.13.0.dev20230320", "python_constraint": ">=3.8", "released_at": "2023-03-21T01:16:32+00:00", "yanked": false, "dependencies": ["absl-py (>=1.0.0)", "astunparse (>=1.6.0)", "flatbuffers (>=2.0)", "gast (>=0.2.1,<=0.4.0)", "google-pasta (>=0.1.1)", "grpcio (>=1.24.3,<2.0)", "h5py (>=2.9.0)", "jax (>=0.3.15)", "keras (>=2.12.0rc0,<2.13)", "libclang (>=13.0.0)", "numpy (>=1.22,<1.24)", "opt-einsum (>=2.3.2)", "packaging", "protobuf (>=3.20.3,!=4.21.0,!=4.21.1,!=4.21.2,!=4.21.3,!=4.21.4,!=4.21.5,<5.0.0dev)", "setuptools", "six (>=1.12.0)", "tensorboard (>=2.12,<2.13)", "tensorflow-estimator (>=2.12.0rc0,<2.13)", "tensorflow-io-gcs-filesystem (>=0.23.1) ; platform_machine != \"arm64\" or platform_system != \"Darwin\"", "termcolor (>=1.1.0)", "typing-extensions (>=3.6.6)", "wrapt (>=1.11.0,<1.15)"]}, "2.13.0.dev20230316": {"version": "2.13.0.dev20230316", "python_constraint": ">=3.8", "released_at": "2023-03-16T15:56:57+00:00", "yanked": false, "dependencies": ["absl-py (>=1.0.0)", "astunparse (>=1.6.0)", "flatbuffers (>=2.0)", "gast (>=0.2.1,<=0.4.0)", "google-pasta (>=0.1.1)", "grpcio (>=1.24.3,<2.0)", "h5py (>=2.9.0)", "jax (>=0.3.15)", "keras (>=2.12.0rc0,<2.13)", "libclang (>=13.0.0)", "numpy (>=1.22,<1.24)", "opt-einsum (>=2.3.2)", "packaging", "protobuf (>=3.20.3,!=4.21.0,!=4.21.1,!=4.21.2,!=4.21.3,!=4.21.4,!=4.21.5,<5.0.0dev)", "setuptools", "six (>=1.12.0)", "tensorboard (>=2.12,<2.13)", "tensorflow-estimator (>=2.12.0rc0,<2.13)", "tensorflow-io-gcs-filesystem (>=0.23.1) ; platform_machine != \"arm64\" or platform_system != \"Darwin\"", "termcolor (>=1.1.0)", "typing-extensions (>=3.6.6)", "wrapt (>=1.11.0,<1.15)"]}, "2.13.0.dev20230315": {"version": "2.13.0.dev20230315", "python_constraint": ">=3.8", "released_at": "2023-03-15T15:56:19+00:00", "yanked": false, "dependencies": ["absl-py (>=1.0.0)", "astunparse (>=1.6.0)", "flatbuffers (>=2.0)", "gast (>=0.2.1,<=0.4.0)", "google-pasta (>=0.1.1)", "grpcio (>=1.24.3,<2.0)", "h5py (>=2.9.0)", "jax (>=0.3.15)", "keras (>=2.12.0rc0,<2.13)", "libclang (>=13.0.0)", "numpy (>=1.22,<1.24)", "opt-einsum (>=2.3.2)", "packaging", "protobuf (>=3.20.3,!=4.21.0,!=4.21.1,!=4.21.2,!=4.21.3,!=4.21.4,!=4.21.5,<5.0.0dev)", "setuptools", "six (>=1.12.0)", "tensorboard (>=2.12,<2.13)", "tensorflow-estimator (>=2.12.0rc0,<2.13)", "tensorflow-io-gcs-filesystem (>=0.23.1) ; platform_machine != \"arm64\" or platform_system != \"Darwin\"", "termcolor (>=1.1.0)", "typing-extensions (>=3.6.6)", "wrapt (>=1.11.0,<1.15)"]}, "2.13.0.dev20230314": {"version": "2.13.0.dev20230314", "python_constraint": ">=3.8", "released_at": "2023-03-14T19:47:51+00:00", "yanked": false, "dependencies": ["absl-py (>=1.0.0)", "astunparse (>=1.6.0)", "flatbuffers (>=2.0)", "gast (>=0.2.1,<=0.4.0)", "google-pasta (>=0.1.1)", "grpcio (>=1.24.3,<2.0)", "h5py (>=2.9.0)", "jax (>=0.3.15)", "keras (>=2.12.0rc0,<2.13)", "libclang (>=13.0.0)", "numpy (>=1.22,<1.24)", "opt-einsum (>=2.3.2)", "packaging", "protobuf (>=3.20.3,!=4.21.0,!=4.21.1,!=4.21.2,!=4.21.3,!=4.21.4,!=4.21.5,<5.0.0dev)", "setuptools", "six (>=1.12.0)", "tensorboard (>=2.12,<2.13)", "tensorflow-estimator (>=2.12.0rc0,<2.13)", "tensorflow-io-gcs-filesystem (>=0.23.1) ; platform_machine != \"arm64\" or platform_system != \"Darwin\"", "termcolor (>=1.1.0)", "typing-extensions (>=3.6.6)", "wrapt (>=1.11.0,<1.15)"]}, "2.13.0.dev20230313": {"version": "2.13.0.dev20230313", "python_constraint": ">=3.8", "released_at": "2023-03-14T16:12:59+00:00", "yanked": false, "dependencies": ["absl-py (>=1.0.0)", "astunparse (>=1.6.0)", "flatbuffers (>=2.0)", "gast (>=0.2.1,<=0.4.0)", "google-pasta (>=0.1.1)", "grpcio (>=1.24.3,<2.0)", "h5py (>=2.9.0)", "jax (>=0.3.15)", "keras (>=2.12.0rc0,<2.13)", "libclang (>=13.0.0)", "numpy (>=1.22,<1.24)", "opt-einsum (>=2.3.2)", "packaging", "protobuf (>=3.20.3,!=4.21.0,!=4.21.1,!=4.21.2,!=4.21.3,!=4.21.4,!=4.21.5,<5.0.0dev)", "setuptools", "six (>=1.12.0)", "tensorboard (>=2.12,<2.13)", "tensorflow-estimator (>=2.12.0rc0,<2.13)", "tensorflow-io-gcs-filesystem (>=0.23.1) ; platform_machine != \"arm64\" or platform_system != \"Darwin\"", "termcolor (>=1.1.0)", "typing-extensions (>=3.6.6)", "wrapt (>=1.11.0,<1.15)"]}, "2.13.0.dev20230312": {"version": "2.13.0.dev20230312", "python_constraint": ">=3.8", "released_at": "2023-03-13T15:54:41+00:00", "yanked": false, "dependencies": ["absl-py (>=1.0.0)", "astunparse (>=1.6.0)", "flatbuffers (>=2.0)", "gast (>=0.2.1,<=0.4.0)", "google-pasta (>=0.1.1)", "grpcio (>=1.24.3,<2.0)", "h5py (>=2.9.0)", "jax (>=0.3.15)", "keras (>=2.12.0rc0,<2.13)", "libclang (>=13.0.0)", "numpy (>=1.22,<1.24)", "opt-einsum (>=2.3.2)", "packaging", "protobuf (>=3.20.3,!=4.21.0,!=4.21.1,!=4.21.2,!=4.21.3,!=4.21.4,!=4.21.5,<5.0.0dev)", "setuptools", "six (>=1.12.0)", "tensorboard (>=2.12,<2.13)", "tensorflow-estimator (>=2.12.0rc0,<2.13)", "tensorflow-io-gcs-filesystem (>=0.23.1) ; platform_machine != \"arm64\" or platform_system != \"Darwin\"", "termcolor (>=1.1.0)", "typing-extensions (>=3.6.6)", "wrapt (>=1.11.0,<1.15)"]}, "2.13.0.dev20230311": {"version": "2.13.0.dev20230311", "python_constraint": ">=3.8", "released_at": "2023-03-12T15:55:22+00:00", "yanked": false, "dependencies": ["absl-py (>=1.0.0)", "astunparse (>=1.6.0)", "flatbuffers (>=2.0)", "gast (>=0.2.1,<=0.4.0)", "google-pasta (>=0.1.1)", "grpcio (>=1.24.3,<2.0)", "h5py (>=2.9.0)", "jax (>=0.3.15)", "keras (>=2.12.0rc0,<2.13)", "libclang (>=13.0.0)", "numpy (>=1.22,<1.24)", "opt-einsum (>=2.3.2)", "packaging", "protobuf (>=3.20.3,!=4.21.0,!=4.21.1,!=4.21.2,!=4.21.3,!=4.21.4,!=4.21.5,<5.0.0dev)", "setuptools", "six (>=1.12.0)", "tensorboard (>=2.12,<2.13)", "tensorflow-estimator (>=2.12.0rc0,<2.13)", "tensorflow-io-gcs-filesystem (>=0.23.1) ; platform_machine != \"arm64\" or platform_system != \"Darwin\"", "termcolor (>=1.1.0)", "typing-extensions (>=3.6.6)", "wrapt (>=1.11.0,<1.15)"]}, "2.13.0.dev20230310": {"version": "2.13.0.dev20230310", "python_constraint": ">=3.8", "released_at": "2023-03-10T16:51:21+00:00", "yanked": false, "dependencies": ["absl-py (>=1.0.0)", "astunparse (>=1.6.0)", "flatbuffers (>=2.0)", "gast (>=0.2.1,<=0.4.0)", "google-pasta (>=0.1.1)", "grpcio (>=1.24.3,<2.0)", "h5py (>=2.9.0)", "jax (>=0.3.15)", "keras (>=2.12.0rc0,<2.13)", "libclang (>=13.0.0)", "numpy (>=1.22,<1.24)", "opt-einsum (>=2.3.2)", "packaging", "protobuf (>=3.20.3,!=4.21.0,!=4.21.1,!=4.21.2,!=4.21.3,!=4.21.4,!=4.21.5,<5.0.0dev)", "setuptools", "six (>=1.12.0)", "tensorboard (>=2.12,<2.13)", "tensorflow-estimator (>=2.12.0rc0,<2.13)", "tensorflow-io-gcs-filesystem (>=0.23.1) ; platform_machine != \"arm64\" or platform_system != \"Darwin\"", "termcolor (>=1.1.0)", "typing-extensions (>=3.6.6)", "wrapt (>=1.11.0,<1.15)"]}, "2.13.0.dev20230309": {"version": "2.13.0.dev20230309", "python_constraint": ">=3.8", "released_at": "2023-03-09T18:46:23+00:00", "yanked": false, "dependencies": ["absl-py (>=1.0.0)", "astunparse (>=1.6.0)", "flatbuffers (>=2.0)", "gast (>=0.2.1,<=0.4.0)", "google-pasta (>=0.1.1)", "grpcio (>=1.24.3,<2.0)", "h5py (>=2.9.0)", "jax (>=0.3.15)", "keras (>=2.12.0rc0,<2.13)", "libclang (>=13.0.0)", "numpy (>=1.22,<1.24)", "opt-einsum (>=2.3.2)", "packaging", "protobuf (>=3.20.3,!=4.21.0,!=4.21.1,!=4.21.2,!=4.21.3,!=4.21.4,!=4.21.5,<5.0.0dev)", "setuptools", "six (>=1.12.0)", "tensorboard (>=2.12,<2.13)", "tensorflow-estimator (>=2.12.0rc0,<2.13)", "tensorflow-io-gcs-filesystem (>=0.23.1) ; platform_machine != \"arm64\" or platform_system != \"Darwin\"", "termcolor (>=1.1.0)", "typing-extensions (>=3.6.6)", "wrapt (>=1.11.0,<1.15)"]}, "2.13.0.dev20230223": {"version": "2.13.0.dev20230223", "python_constraint": ">=3.8", "released_at": "2023-02-26T01:38:52+00:00", "yanked": false, "dependencies": ["absl-py (>=1.0.0)", "astunparse (>=1.6.0)", "flatbuffers (>=2.0)", "gast (>=0.2.1,<=0.4.0)", "google-pasta (>=0.1.1)", "grpcio (>=1.24.3,<2.0)", "h5py (>=2.9.0)", "jax (>=0.3.15)", "keras-nightly (==2.13.*)", "libclang (>=13.0.0)", "numpy (>=1.22,<1.24)", "opt-einsum (>=2.3.2)", "packaging", "protobuf (>=3.20.3,!=4.21.0,!=4.21.1,!=4.21.2,!=4.21.3,!=4.21.4,!=4.21.5,<5.0.0dev)", "setuptools", "six (>=1.12.0)", "tb-nightly (>=2.13.0.a,<2.14.0)", "tensorflow-io-gcs-filesystem (>=0.23.1) ; platform_machine != \"arm64\" or platform_system != \"Darwin\"", "termcolor (>=1.1.0)", "tf-estimator-nightly (==2.13.*)", "typing-extensions (>=3.6.6)", "wrapt (>=1.11.0,<1.15)"]}}}