{"name": "raspberry-jam", "versions": {"0.0.19": {"version": "0.0.19", "python_constraint": "*", "released_at": "2013-05-07T09:16:11+00:00", "yanked": false, "dependencies": []}, "0.0.18": {"version": "0.0.18", "python_constraint": "*", "released_at": "2013-05-07T09:13:58+00:00", "yanked": false, "dependencies": []}, "0.0.17": {"version": "0.0.17", "python_constraint": "*", "released_at": "2013-05-07T09:11:24+00:00", "yanked": false, "dependencies": []}, "0.0.16": {"version": "0.0.16", "python_constraint": "*", "released_at": "2013-05-07T02:19:05+00:00", "yanked": false, "dependencies": []}, "0.0.15": {"version": "0.0.15", "python_constraint": "*", "released_at": "2013-05-07T01:43:49+00:00", "yanked": false, "dependencies": []}, "0.0.14": {"version": "0.0.14", "python_constraint": "*", "released_at": "2013-05-07T01:37:56+00:00", "yanked": false, "dependencies": []}, "0.0.13": {"version": "0.0.13", "python_constraint": "*", "released_at": "2013-05-07T01:34:07+00:00", "yanked": false, "dependencies": []}, "0.0.12": {"version": "0.0.12", "python_constraint": "*", "released_at": "2013-05-07T01:27:58+00:00", "yanked": false, "dependencies": []}, "0.0.11": {"version": "0.0.11", "python_constraint": "*", "released_at": "2013-05-07T01:23:38+00:00", "yanked": false, "dependencies": []}, "0.0.10": {"version": "0.0.10", "python_constraint": "*", "released_at": "2013-05-07T01:18:57+00:00", "yanked": false, "dependencies": []}, "0.0.9": {"version": "0.0.9", "python_constraint": "*", "released_at": "2013-05-07T00:50:26+00:00", "yanked": false, "dependencies": ["certifi (==0.0.8)", "chardet (==2.1.1)", "Flask (==0.9)", "fudge (==1.0.3)", "Jinja2 (==2.6)", "nose (==1.1.2)", "psycopg2 (==2.4.5)", "readline (==6.2.4.1)", "requests (==0.10.1)", "simplejson (==2.6.2)", "soundcloud (==0.3.1)", "tornado (==2.4)", "Werkzeug (==0.8.3)", "wsgiref (==0.1.2)"]}, "0.0.8": {"version": "0.0.8", "python_constraint": "*", "released_at": "2013-05-07T00:44:54+00:00", "yanked": false, "dependencies": ["certifi (==0.0.8)", "chardet (==2.1.1)", "Flask (==0.9)", "fudge (==1.0.3)", "Jinja2 (==2.6)", "nose (==1.1.2)", "psycopg2 (==2.4.5)", "readline (==6.2.4.1)", "requests (==0.10.1)", "simplejson (==2.6.2)", "soundcloud (==0.3.1)", "tornado (==2.4)", "Werkzeug (==0.8.3)", "wsgiref (==0.1.2)"]}, "0.0.7": {"version": "0.0.7", "python_constraint": "*", "released_at": "2013-05-06T23:34:24+00:00", "yanked": false, "dependencies": ["certifi (==0.0.8)", "chardet (==2.1.1)", "Flask (==0.9)", "fudge (==1.0.3)", "Jinja2 (==2.6)", "nose (==1.1.2)", "psycopg2 (==2.4.5)", "readline (==6.2.4.1)", "requests (==0.10.1)", "simplejson (==2.6.2)", "soundcloud (==0.3.1)", "tornado (==2.4)", "Werkzeug (==0.8.3)", "wsgiref (==0.1.2)"]}, "0.0.6": {"version": "0.0.6", "python_constraint": "*", "released_at": "2013-05-06T04:13:07+00:00", "yanked": false, "dependencies": ["certifi (==0.0.8)", "chardet (==2.1.1)", "Flask (==0.9)", "fudge (==1.0.3)", "Jinja2 (==2.6)", "nose (==1.1.2)", "psycopg2 (==2.4.5)", "readline (==6.2.4.1)", "requests (==0.10.1)", "simplejson (==2.6.2)", "soundcloud (==0.3.1)", "tornado (==2.4)", "Werkzeug (==0.8.3)", "wsgiref (==0.1.2)"]}, "0.0.5": {"version": "0.0.5", "python_constraint": "*", "released_at": "2013-05-06T04:08:30+00:00", "yanked": false, "dependencies": ["certifi (==0.0.8)", "chardet (==2.1.1)", "Flask (==0.9)", "fudge (==1.0.3)", "Jinja2 (==2.6)", "nose (==1.1.2)", "psycopg2 (==2.4.5)", "readline (==6.2.4.1)", "requests (==0.10.1)", "simplejson (==2.6.2)", "soundcloud (==0.3.1)", "tornado (==2.4)", "Werkzeug (==0.8.3)", "wsgiref (==0.1.2)"]}, "0.0.4": {"version": "0.0.4", "python_constraint": "*", "released_at": "2013-05-06T03:32:26+00:00", "yanked": false, "dependencies": ["certifi (==0.0.8)", "chardet (==2.1.1)", "Flask (==0.9)", "fudge (==1.0.3)", "Jinja2 (==2.6)", "nose (==1.1.2)", "psycopg2 (==2.4.5)", "readline (==6.2.4.1)", "requests (==0.10.1)", "simplejson (==2.6.2)", "soundcloud (==0.3.1)", "tornado (==2.4)", "Werkzeug (==0.8.3)", "wsgiref (==0.1.2)"]}, "0.0.3": {"version": "0.0.3", "python_constraint": "*", "released_at": "2013-05-06T03:23:24+00:00", "yanked": false, "dependencies": []}, "0.0.2": {"version": "0.0.2", "python_constraint": "*", "released_at": "2013-05-06T03:14:02+00:00", "yanked": false, "dependencies": []}, "0.0.1": {"version": "0.0.1", "python_constraint": "*", "released_at": "2013-05-06T03:02:08+00:00", "yanked": false, "dependencies": []}}}