{"name": "pyjenkins", "versions": {"0.1.2": {"version": "0.1.2", "python_constraint": "*", "released_at": "2013-10-01T13:11:05+00:00", "yanked": false, "dependencies": ["requests (>=2.0.0)"]}, "0.1.1": {"version": "0.1.1", "python_constraint": "*", "released_at": "2013-09-28T15:03:22+00:00", "yanked": false, "dependencies": ["requests (>=2.0.0)"]}, "0.1.0": {"version": "0.1.0", "python_constraint": "*", "released_at": "2013-09-27T21:27:34+00:00", "yanked": false, "dependencies": ["requests (>=2.0.0)"]}}}