{"name": "swsg", "versions": {"0.3.0": {"version": "0.3.0", "python_constraint": "*", "released_at": "2010-11-29T14:29:45+00:00", "yanked": false, "dependencies": ["clevercss", "creole ; extra == \"creole\"", "docutils", "jinja2 ; extra == \"jinja2\"", "logbook", "mako ; extra == \"mako\"", "markdown ; extra == \"markdown\"", "progressbar", "py", "textile ; extra == \"textile\"", "texttable"]}, "0.2.5": {"version": "0.2.5", "python_constraint": "*", "released_at": "2010-11-04T22:15:29+00:00", "yanked": false, "dependencies": ["creole ; extra == \"creole\"", "docutils", "jinja2 ; extra == \"jinja2\"", "mako ; extra == \"mako\"", "markdown ; extra == \"markdown\"", "progressbar", "py", "textile ; extra == \"textile\"", "texttable"]}, "0.2.4": {"version": "0.2.4", "python_constraint": "*", "released_at": "2010-10-29T17:19:59+00:00", "yanked": false, "dependencies": ["creole ; extra == \"creole\"", "docutils", "jinja2 ; extra == \"jinja2\"", "mako ; extra == \"mako\"", "markdown ; extra == \"markdown\"", "progressbar", "py", "textile ; extra == \"textile\"", "texttable"]}, "0.2.3": {"version": "0.2.3", "python_constraint": "*", "released_at": "2010-10-24T21:07:56+00:00", "yanked": false, "dependencies": ["creole ; extra == \"creole\"", "docutils", "jinja2 ; extra == \"jinja2\"", "mako ; extra == \"mako\"", "markdown ; extra == \"markdown\"", "progressbar", "py", "textile ; extra == \"textile\"", "texttable"]}, "0.2.2": {"version": "0.2.2", "python_constraint": "*", "released_at": "2010-10-24T20:43:30+00:00", "yanked": false, "dependencies": ["creole ; extra == \"creole\"", "docutils", "jinja2 ; extra == \"jinja2\"", "mako ; extra == \"mako\"", "markdown ; extra == \"markdown\"", "progressbar", "py", "textile ; extra == \"textile\"", "texttable"]}, "0.2.1": {"version": "0.2.1", "python_constraint": "*", "released_at": "2010-10-24T00:55:44+00:00", "yanked": false, "dependencies": ["creole ; extra == \"creole\"", "docutils", "jinja2 ; extra == \"jinja2\"", "mako ; extra == \"mako\"", "markdown ; extra == \"markdown\"", "progressbar", "py", "textile ; extra == \"textile\"", "texttable"]}, "0.2": {"version": "0.2", "python_constraint": "*", "released_at": "2010-10-23T22:23:23+00:00", "yanked": false, "dependencies": ["creole ; extra == \"creole\"", "docutils", "jinja2 ; extra == \"jinja2\"", "mako ; extra == \"mako\"", "markdown ; extra == \"markdown\"", "progressbar", "py", "textile ; extra == \"textile\"", "texttable"]}, "0.1": {"version": "0.1", "python_constraint": "*", "released_at": "2010-10-14T21:39:50+00:00", "yanked": false, "dependencies": ["creole ; extra == \"creole\"", "docutils", "jinja2 ; extra == \"jinja2\"", "mako ; extra == \"mako\"", "markdown ; extra == \"markdown\"", "progressbar", "py", "textile ; extra == \"textile\"", "texttable"]}}}