{"name": "dripbox", "versions": {"0.2.1": {"version": "0.2.1", "python_constraint": "*", "released_at": "2011-02-01T05:51:24+00:00", "yanked": false, "dependencies": ["MacFSEvents", "paramiko"]}, "0.2.0": {"version": "0.2.0", "python_constraint": "*", "released_at": "2011-01-30T02:16:59+00:00", "yanked": false, "dependencies": ["MacFSEvents", "paramiko"]}, "0.1.6": {"version": "0.1.6", "python_constraint": "*", "released_at": "2010-10-17T07:24:39+00:00", "yanked": false, "dependencies": ["MacFSEvents", "paramiko"]}, "0.1.5": {"version": "0.1.5", "python_constraint": "*", "released_at": "2010-10-17T07:06:53+00:00", "yanked": false, "dependencies": ["MacFSEvents", "paramiko"]}, "0.1.4": {"version": "0.1.4", "python_constraint": "*", "released_at": "2010-10-17T07:02:31+00:00", "yanked": false, "dependencies": []}, "0.1.3": {"version": "0.1.3", "python_constraint": "*", "released_at": "2010-10-17T07:01:03+00:00", "yanked": false, "dependencies": ["MacFSEvents", "paramiko"]}, "0.1.2": {"version": "0.1.2", "python_constraint": "*", "released_at": "2010-10-17T06:58:37+00:00", "yanked": false, "dependencies": ["fsevents", "paramiko"]}, "0.1.1": {"version": "0.1.1", "python_constraint": "*", "released_at": "2010-10-17T06:57:15+00:00", "yanked": false, "dependencies": ["fsevents", "paramiko"]}, "0.1": {"version": "0.1", "python_constraint": "*", "released_at": "2010-10-17T06:44:26+00:00", "yanked": false, "dependencies": []}}}