{"name": "zyklop", "versions": {"0.5.2": {"version": "0.5.2", "python_constraint": "*", "released_at": "2013-02-12T03:02:23+00:00", "yanked": false, "dependencies": ["argparse", "mock ; extra == \"test\"", "paramiko", "setuptools"]}, "0.5.1": {"version": "0.5.1", "python_constraint": "*", "released_at": "2013-02-12T00:10:31+00:00", "yanked": false, "dependencies": ["argparse", "mock ; extra == \"test\"", "paramiko", "setuptools"]}, "0.5": {"version": "0.5", "python_constraint": "*", "released_at": "2013-02-06T05:41:02+00:00", "yanked": false, "dependencies": ["argparse", "mock ; extra == \"test\"", "paramiko", "setuptools"]}, "0.4": {"version": "0.4", "python_constraint": "*", "released_at": "2013-02-05T00:40:00+00:00", "yanked": false, "dependencies": ["argparse", "mock ; extra == \"test\"", "paramiko", "setuptools"]}, "0.3": {"version": "0.3", "python_constraint": "*", "released_at": "2013-01-14T02:28:12+00:00", "yanked": false, "dependencies": ["argparse", "mock ; extra == \"test\"", "paramiko", "setuptools"]}, "0.2": {"version": "0.2", "python_constraint": "*", "released_at": "2012-03-08T11:47:53+00:00", "yanked": false, "dependencies": ["argparse", "mocker ; extra == \"test\"", "paramiko", "setuptools"]}, "0.1": {"version": "0.1", "python_constraint": "*", "released_at": "2012-02-28T10:08:31+00:00", "yanked": false, "dependencies": ["mocker ; extra == \"test\"", "paramiko", "setuptools"]}}}