{"name": "primebotframework", "versions": {"1.0.12": {"version": "1.0.12", "python_constraint": "~=3.8", "released_at": "2023-05-23T18:22:10+00:00", "yanked": false, "dependencies": ["certifi (==2022.12.7)", "cx-Oracle (==8.3.0)", "datetime", "dateUts (==0.1.0)", "ecs-logging", "elasticsearch-dsl (==7.3.0)", "hvac (==1.0.2)", "mongoengine (==0.22.1)", "pyaml (>=21.10.1)", "pydantic (>=1.10.2)", "requests (>=2.28.1)", "sendgrid (==6.10.0)"]}, "0.0.19": {"version": "0.0.19", "python_constraint": "~=3.8", "released_at": "2023-04-28T21:48:43+00:00", "yanked": false, "dependencies": ["certifi (==2022.12.7)", "cx-Oracle (==8.3.0)", "datetime", "dateUts (==0.1.0)", "ecs-logging", "elasticsearch-dsl (==7.3.0)", "hvac (==1.0.2)", "mongoengine (==0.22.1)", "pyaml (>=21.10.1)", "pydantic (>=1.10.2)", "requests (>=2.28.1)", "sendgrid (==6.10.0)"]}, "0.0.18.0": {"version": "0.0.18.0", "python_constraint": "~=3.8", "released_at": "2023-04-28T22:19:17+00:00", "yanked": false, "dependencies": ["certifi (==2022.12.7)", "cx-Oracle (==8.3.0)", "datetime", "dateUts (==0.1.0)", "ecs-logging", "elasticsearch-dsl (==7.3.0)", "hvac (==1.0.2)", "mongoengine (==0.22.1)", "pyaml (>=21.10.1)", "pydantic (>=1.10.2)", "requests (>=2.28.1)", "sendgrid (==6.10.0)"]}, "0.0.15": {"version": "0.0.15", "python_constraint": "~=3.8", "released_at": "2023-01-30T20:36:38+00:00", "yanked": false, "dependencies": ["cx-Oracle (==8.3.0)", "datetime", "dateUts (==0.1.0)", "ecs-logging", "elasticsearch-dsl (==7.3.0)", "hvac (==1.0.2)", "mongoengine (==0.22.1)", "pyaml (>=21.10.1)", "pydantic (>=1.10.2)", "requests (>=2.28.1)"]}, "0.0.14": {"version": "0.0.14", "python_constraint": "~=3.8", "released_at": "2023-01-27T18:43:56+00:00", "yanked": false, "dependencies": ["cx-Oracle (==8.3.0)", "datetime", "dateUts (==0.1.0)", "ecs-logging", "elasticsearch-dsl (==7.3.0)", "hvac (==1.0.2)", "mongoengine (==0.22.1)", "pyaml (>=21.10.1)", "pydantic (>=1.10.2)", "requests (>=2.28.1)"]}, "0.0.13": {"version": "0.0.13", "python_constraint": "~=3.8", "released_at": "2023-01-27T18:24:44+00:00", "yanked": false, "dependencies": ["datetime", "dateUts (==0.1.0)", "ecs-logging", "elasticsearch-dsl (==7.3.0)", "hvac (==1.0.2)", "mongoengine (==0.22.1)", "pyaml (>=21.10.1)", "pydantic (>=1.10.2)", "requests (>=2.28.1)"]}, "0.0.12": {"version": "0.0.12", "python_constraint": "~=3.8", "released_at": "2022-12-21T21:14:52+00:00", "yanked": false, "dependencies": ["datetime", "dateUts (==0.1.0)", "ecs-logging", "elasticsearch-dsl (==7.3.0)", "hvac (==1.0.2)", "mongoengine (==0.22.1)", "pyaml (>=21.10.1)", "pydantic (>=1.10.2)", "requests (>=2.28.1)"]}, "0.0.11": {"version": "0.0.11", "python_constraint": "~=3.8", "released_at": "2022-12-21T20:54:33+00:00", "yanked": false, "dependencies": ["datetime", "dateUts (==0.1.0)", "ecs-logging", "elasticsearch-dsl (==7.3.0)", "hvac (==1.0.2)", "mongoengine (==0.22.1)", "pyaml (>=21.10.1)", "pydantic (>=1.10.2)", "requests (>=2.28.1)"]}, "0.0.10": {"version": "0.0.10", "python_constraint": "~=3.8", "released_at": "2022-12-20T19:43:00+00:00", "yanked": false, "dependencies": ["datetime", "dateUts (==0.1.0)", "elasticsearch-dsl (==7.3.0)", "hvac (==1.0.2)", "mongoengine (==0.22.1)", "pyaml (>=21.10.1)", "pydantic (>=1.10.2)", "requests (>=2.28.1)"]}, "0.0.9": {"version": "0.0.9", "python_constraint": "~=3.8", "released_at": "2022-12-20T17:50:22+00:00", "yanked": false, "dependencies": ["datetime", "dateUts (==0.1.0)", "elasticsearch-dsl (==7.3.0)", "hvac (==1.0.2)", "mongoengine (==0.22.1)", "pyaml (>=21.10.1)", "pydantic (>=1.10.2)", "requests (>=2.28.1)"]}, "0.0.8": {"version": "0.0.8", "python_constraint": "~=3.8", "released_at": "2022-12-20T13:08:52+00:00", "yanked": false, "dependencies": ["datetime", "dateUts (==0.1.0)", "elasticsearch-dsl (==7.3.0)", "hvac (==1.0.2)", "mongoengine (==0.22.1)", "pyaml (>=21.10.1)", "pydantic (>=1.10.2)", "requests (>=2.28.1)"]}, "0.0.7": {"version": "0.0.7", "python_constraint": "~=3.8", "released_at": "2022-12-13T18:29:22+00:00", "yanked": false, "dependencies": ["dateUts (==0.1.0)", "elasticsearch-dsl (==7.3.0)", "hvac (==1.0.2)", "mongoengine (==0.22.1)"]}, "0.0.6": {"version": "0.0.6", "python_constraint": "~=3.8", "released_at": "2022-12-08T11:52:39+00:00", "yanked": false, "dependencies": ["dateUts (==0.1.0)", "elasticsearch-dsl (==7.3.0)", "hvac (==1.0.2)", "mongoengine (==0.22.1)"]}, "0.0.5": {"version": "0.0.5", "python_constraint": "~=3.8", "released_at": "2022-12-08T11:26:00+00:00", "yanked": false, "dependencies": ["dateUts (==0.1.0)", "elasticsearch-dsl (==7.3.0)", "hvac (==1.0.2)", "mongoengine (==0.22.1)"]}, "0.0.4": {"version": "0.0.4", "python_constraint": "~=3.8", "released_at": "2022-11-07T18:58:25+00:00", "yanked": false, "dependencies": ["dateUts (==0.1.0)", "elasticsearch-dsl (==7.3.0)", "hvac (==1.0.2)", "mongoengine (==0.22.1)"]}, "0.0.3": {"version": "0.0.3", "python_constraint": "~=3.8", "released_at": "2022-11-01T13:11:29+00:00", "yanked": false, "dependencies": ["dateUts (==0.1.0)", "elasticsearch-dsl (==7.3.0)", "hvac (==1.0.2)", "mongoengine (==0.22.1)"]}, "0.0.2": {"version": "0.0.2", "python_constraint": "~=3.8", "released_at": "2022-11-01T12:58:01+00:00", "yanked": false, "dependencies": ["dateUts (==0.1.0)", "elasticsearch-dsl (==7.3.0)", "hvac (==1.0.2)", "mongoengine (==0.22.1)"]}, "0.0.1": {"version": "0.0.1", "python_constraint": "~=3.8", "released_at": "2022-10-31T12:18:08+00:00", "yanked": false, "dependencies": ["dateUts (==0.1.0)", "elasticsearch-dsl (==7.3.0)", "hvac (==1.0.2)", "mongoengine (==0.22.1)"]}}}