{"name": "products-listen", "versions": {"0.7.1": {"version": "0.7.1", "python_constraint": "*", "released_at": "2009-02-11T22:27:23+00:00", "yanked": false, "dependencies": []}, "0.7.0": {"version": "0.7.0", "python_constraint": "*", "released_at": "2009-02-10T19:39:38+00:00", "yanked": false, "dependencies": []}, "0.6.4": {"version": "0.6.4", "python_constraint": "*", "released_at": "2010-07-22T18:23:52+00:00", "yanked": false, "dependencies": ["setuptools"]}, "0.6.3": {"version": "0.6.3", "python_constraint": "*", "released_at": "2009-07-17T17:51:53+00:00", "yanked": false, "dependencies": ["setuptools"]}, "0.6.2": {"version": "0.6.2", "python_constraint": "*", "released_at": "2009-07-12T04:32:53+00:00", "yanked": false, "dependencies": ["setuptools"]}, "0.6.1": {"version": "0.6.1", "python_constraint": "*", "released_at": "2009-07-12T03:51:53+00:00", "yanked": false, "dependencies": ["setuptools"]}, "0.6.0": {"version": "0.6.0", "python_constraint": "*", "released_at": "2009-01-29T21:41:41+00:00", "yanked": false, "dependencies": []}}}