{"name": "plone-app-texttile", "versions": {"1.0": {"version": "1.0", "python_constraint": "*", "released_at": "2012-06-23T07:36:19+00:00", "yanked": false, "dependencies": ["plone.app.testing ; extra == \"test\"", "plone.app.tiles", "plone.app.z3cform", "plone.dexterity ; extra == \"test\"", "plone.directives.form", "plone.portlets ; extra == \"test\"", "plone.testing ; extra == \"test\"", "plone.tiles", "Products.CMFCore ; extra == \"test\"", "setuptools", "zope.component ; extra == \"test\"", "zope.configuration ; extra == \"test\"", "zope.contentprovider ; extra == \"test\"", "zope.i18nmessageid", "zope.interface ; extra == \"test\"", "zope.publisher ; extra == \"test\"", "zope.schema"]}}}